[
  {
    "itemId": "T5_MAIN_AXE",
    "itemName": "Expert's Battleaxe",
    "itemTag": "@ITEMS_T5_MAIN_AXE",
    "selectedMarket": "Martlock",
    "otherMarket": "Black Market",
    "Buying_Price": 5095,
    "Selling_Price": 93160,
    "silver_profit": 88065,
    "Ratio": 0.9453091455560326
  },
  {
    "itemId": "T4_ARMOR_LEATHER_SET3@1",
    "itemName": "Adept's Assassin Jacket",
    "itemTag": "@ITEMS_T4_ARMOR_LEATHER_SET3",
    "selectedMarket": "Martlock",
    "otherMarket": "Black Market",
    "Buying_Price": 1100,
    "Selling_Price": 5110,
    "silver_profit": 4010,
    "Ratio": 0.7847358121330724
  },
  {
    "itemId": "T2_HEAD_PLATE_SET1",
    "itemName": "Novice's Soldier Helmet",
    "itemTag": "@ITEMS_T2_HEAD_PLATE_SET1",
    "selectedMarket": "Martlock",
    "otherMarket": "Black Market",
    "Buying_Price": 35,
    "Selling_Price": 161,
    "silver_profit": 126,
    "Ratio": 0.782608695652174
  },
  {
    "itemId": "T4_2H_AXE",
    "itemName": "Adept's Greataxe",
    "itemTag": "@ITEMS_T4_2H_AXE",
    "selectedMarket": "Martlock",
    "otherMarket": "Black Market",
    "Buying_Price": 1500,
    "Selling_Price": 5840,
    "silver_profit": 4340,
    "Ratio": 0.7431506849315068
  },
  {
    "itemId": "T3_SHOES_PLATE_SET1",
    "itemName": "Journeyman's Soldier Boots",
    "itemTag": "@ITEMS_T3_SHOES_PLATE_SET1",
    "selectedMarket": "Martlock",
    "otherMarket": "Black Market",
    "Buying_Price": 217,
    "Selling_Price": 782,
    "silver_profit": 565,
    "Ratio": 0.7225063938618926
  },
  {
    "itemId": "T4_HEAD_PLATE_SET1",
    "itemName": "Adept's Soldier Helmet",
    "itemTag": "@ITEMS_T4_HEAD_PLATE_SET1",
    "selectedMarket": "Martlock",
    "otherMarket": "Black Market",
    "Buying_Price": 337,
    "Selling_Price": 1183,
    "silver_profit": 846,
    "Ratio": 0.7151310228233305
  },
  {
    "itemId": "T5_SHOES_PLATE_SET1",
    "itemName": "Expert's Soldier Boots",
    "itemTag": "@ITEMS_T5_SHOES_PLATE_SET1",
    "selectedMarket": "Martlock",
    "otherMarket": "Black Market",
    "Buying_Price": 1100,
    "Selling_Price": 3843,
    "silver_profit": 2743,
    "Ratio": 0.7137652875357794
  },
  {
    "itemId": "T4_SHOES_PLATE_SET3",
    "itemName": "Adept's Guardian Boots",
    "itemTag": "@ITEMS_T4_SHOES_PLATE_SET3",
    "selectedMarket": "Martlock",
    "otherMarket": "Black Market",
    "Buying_Price": 350,
    "Selling_Price": 1183,
    "silver_profit": 833,
    "Ratio": 0.7041420118343196
  },
  {
    "itemId": "T4_SHOES_CLOTH_SET1",
    "itemName": "Adept's Scholar Sandals",
    "itemTag": "@ITEMS_T4_SHOES_CLOTH_SET1",
    "selectedMarket": "Martlock",
    "otherMarket": "Black Market",
    "Buying_Price": 303,
    "Selling_Price": 1001,
    "silver_profit": 698,
    "Ratio": 0.6973026973026973
  },
  {
    "itemId": "T2_2H_BOW",
    "itemName": "Novice's Bow",
    "itemTag": "@ITEMS_T2_2H_BOW",
    "selectedMarket": "Martlock",
    "otherMarket": "Black Market",
    "Buying_Price": 119,
    "Selling_Price": 364,
    "silver_profit": 245,
    "Ratio": 0.6730769230769231
  },
  {
    "itemId": "T4_SHOES_CLOTH_SET3",
    "itemName": "Adept's Mage Sandals",
    "itemTag": "@ITEMS_T4_SHOES_CLOTH_SET3",
    "selectedMarket": "Martlock",
    "otherMarket": "Black Market",
    "Buying_Price": 389,
    "Selling_Price": 1183,
    "silver_profit": 794,
    "Ratio": 0.6711749788672866
  },
  {
    "itemId": "T4_SHOES_CLOTH_SET2",
    "itemName": "Adept's Cleric Sandals",
    "itemTag": "@ITEMS_T4_SHOES_CLOTH_SET2",
    "selectedMarket": "Martlock",
    "otherMarket": "Black Market",
    "Buying_Price": 390,
    "Selling_Price": 1183,
    "silver_profit": 793,
    "Ratio": 0.6703296703296703
  },
  {
    "itemId": "T4_SHOES_LEATHER_SET1",
    "itemName": "Adept's Mercenary Shoes",
    "itemTag": "@ITEMS_T4_SHOES_LEATHER_SET1",
    "selectedMarket": "Martlock",
    "otherMarket": "Black Market",
    "Buying_Price": 517,
    "Selling_Price": 1456,
    "silver_profit": 939,
    "Ratio": 0.6449175824175825
  },
  {
    "itemId": "T4_HEAD_PLATE_SET3",
    "itemName": "Adept's Guardian Helmet",
    "itemTag": "@ITEMS_T4_HEAD_PLATE_SET3",
    "selectedMarket": "Martlock",
    "otherMarket": "Black Market",
    "Buying_Price": 424,
    "Selling_Price": 1183,
    "silver_profit": 759,
    "Ratio": 0.6415891800507185
  },
  {
    "itemId": "T4_HEAD_PLATE_SET2",
    "itemName": "Adept's Knight Helmet",
    "itemTag": "@ITEMS_T4_HEAD_PLATE_SET2",
    "selectedMarket": "Martlock",
    "otherMarket": "Black Market",
    "Buying_Price": 328,
    "Selling_Price": 910,
    "silver_profit": 582,
    "Ratio": 0.6395604395604395
  },
  {
    "itemId": "T4_ARMOR_CLOTH_SET1",
    "itemName": "Adept's Scholar Robe",
    "itemTag": "@ITEMS_T4_ARMOR_CLOTH_SET1",
    "selectedMarket": "Martlock",
    "otherMarket": "Black Market",
    "Buying_Price": 597,
    "Selling_Price": 1647,
    "silver_profit": 1050,
    "Ratio": 0.6375227686703097
  },
  {
    "itemId": "T4_HEAD_LEATHER_SET3",
    "itemName": "Adept's Assassin Hood",
    "itemTag": "@ITEMS_T4_HEAD_LEATHER_SET3",
    "selectedMarket": "Martlock",
    "otherMarket": "Black Market",
    "Buying_Price": 866,
    "Selling_Price": 2366,
    "silver_profit": 1500,
    "Ratio": 0.6339814032121724
  },
  {
    "itemId": "T4_ARMOR_LEATHER_SET2",
    "itemName": "Adept's Hunter Jacket",
    "itemTag": "@ITEMS_T4_ARMOR_LEATHER_SET2",
    "selectedMarket": "Martlock",
    "otherMarket": "Black Market",
    "Buying_Price": 884,
    "Selling_Price": 2379,
    "silver_profit": 1495,
    "Ratio": 0.6284153005464481
  },
  {
    "itemId": "T2_BAG",
    "itemName": "Novice's Bag",
    "itemTag": "@ITEMS_T2_BAG",
    "selectedMarket": "Martlock",
    "otherMarket": "Black Market",
    "Buying_Price": 420,
    "Selling_Price": 1088,
    "silver_profit": 668,
    "Ratio": 0.6139705882352942
  },
  {
    "itemId": "T3_CAPE",
    "itemName": "Journeyman's Cape",
    "itemTag": "@ITEMS_T3_CAPE",
    "selectedMarket": "Martlock",
    "otherMarket": "Black Market",
    "Buying_Price": 539,
    "Selling_Price": 1380,
    "silver_profit": 841,
    "Ratio": 0.6094202898550725
  },
  {
    "itemId": "T4_HEAD_LEATHER_SET1",
    "itemName": "Adept's Mercenary Hood",
    "itemTag": "@ITEMS_T4_HEAD_LEATHER_SET1",
    "selectedMarket": "Martlock",
    "otherMarket": "Black Market",
    "Buying_Price": 571,
    "Selling_Price": 1456,
    "silver_profit": 885,
    "Ratio": 0.6078296703296703
  },
  {
    "itemId": "T3_ARMOR_CLOTH_SET1",
    "itemName": "Journeyman's Scholar Robe",
    "itemTag": "@ITEMS_T3_ARMOR_CLOTH_SET1",
    "selectedMarket": "Martlock",
    "otherMarket": "Black Market",
    "Buying_Price": 300,
    "Selling_Price": 728,
    "silver_profit": 428,
    "Ratio": 0.5879120879120879
  },
  {
    "itemId": "T4_ARMOR_CLOTH_SET3",
    "itemName": "Adept's Mage Robe",
    "itemTag": "@ITEMS_T4_ARMOR_CLOTH_SET3",
    "selectedMarket": "Martlock",
    "otherMarket": "Black Market",
    "Buying_Price": 982,
    "Selling_Price": 2379,
    "silver_profit": 1397,
    "Ratio": 0.5872215216477512
  },
  {
    "itemId": "T4_2H_DUALSWORD",
    "itemName": "Adept's Dual Swords",
    "itemTag": "@ITEMS_T4_2H_DUALSWORD",
    "selectedMarket": "Martlock",
    "otherMarket": "Black Market",
    "Buying_Price": 1889,
    "Selling_Price": 4380,
    "silver_profit": 2491,
    "Ratio": 0.5687214611872146
  },
  {
    "itemId": "T4_OFF_BOOK",
    "itemName": "Adept's Tome of Spells",
    "itemTag": "@ITEMS_T4_OFF_BOOK",
    "selectedMarket": "Martlock",
    "otherMarket": "Black Market",
    "Buying_Price": 552,
    "Selling_Price": 1274,
    "silver_profit": 722,
    "Ratio": 0.5667189952904239
  },
  {
    "itemId": "T4_HEAD_CLOTH_SET3",
    "itemName": "Adept's Mage Cowl",
    "itemTag": "@ITEMS_T4_HEAD_CLOTH_SET3",
    "selectedMarket": "Martlock",
    "otherMarket": "Black Market",
    "Buying_Price": 521,
    "Selling_Price": 1183,
    "silver_profit": 662,
    "Ratio": 0.5595942519019442
  },
  {
    "itemId": "T4_ARMOR_PLATE_SET3",
    "itemName": "Adept's Guardian Armor",
    "itemTag": "@ITEMS_T4_ARMOR_PLATE_SET3",
    "selectedMarket": "Martlock",
    "otherMarket": "Black Market",
    "Buying_Price": 849,
    "Selling_Price": 1830,
    "silver_profit": 981,
    "Ratio": 0.5360655737704918
  },
  {
    "itemId": "T4_HEAD_LEATHER_SET2",
    "itemName": "Adept's Hunter Hood",
    "itemTag": "@ITEMS_T4_HEAD_LEATHER_SET2",
    "selectedMarket": "Martlock",
    "otherMarket": "Black Market",
    "Buying_Price": 597,
    "Selling_Price": 1274,
    "silver_profit": 677,
    "Ratio": 0.5313971742543171
  },
  {
    "itemId": "T5_HEAD_CLOTH_SET3",
    "itemName": "Expert's Mage Cowl",
    "itemTag": "@ITEMS_T5_HEAD_CLOTH_SET3",
    "selectedMarket": "Martlock",
    "otherMarket": "Black Market",
    "Buying_Price": 3318,
    "Selling_Price": 6954,
    "silver_profit": 3636,
    "Ratio": 0.5228645383951682
  },
  {
    "itemId": "T4_SHOES_LEATHER_SET3",
    "itemName": "Adept's Assassin Shoes",
    "itemTag": "@ITEMS_T4_SHOES_LEATHER_SET3",
    "selectedMarket": "Martlock",
    "otherMarket": "Black Market",
    "Buying_Price": 440,
    "Selling_Price": 910,
    "silver_profit": 470,
    "Ratio": 0.5164835164835165
  },
  {
    "itemId": "T6_HEAD_LEATHER_SET1@1",
    "itemName": "Master's Mercenary Hood",
    "itemTag": "@ITEMS_T6_HEAD_LEATHER_SET1",
    "selectedMarket": "Martlock",
    "otherMarket": "Black Market",
    "Buying_Price": 14985,
    "Selling_Price": 30660,
    "silver_profit": 15675,
    "Ratio": 0.511252446183953
  },
  {
    "itemId": "T4_HEAD_CLOTH_SET2",
    "itemName": "Adept's Cleric Cowl",
    "itemTag": "@ITEMS_T4_HEAD_CLOTH_SET2",
    "selectedMarket": "Martlock",
    "otherMarket": "Black Market",
    "Buying_Price": 587,
    "Selling_Price": 1183,
    "silver_profit": 596,
    "Ratio": 0.503803888419273
  },
  {
    "itemId": "T5_OFF_TOWERSHIELD_UNDEAD",
    "itemName": "Expert's Sarcophagus",
    "itemTag": "@ITEMS_T5_OFF_TOWERSHIELD_UNDEAD",
    "selectedMarket": "Martlock",
    "otherMarket": "Black Market",
    "Buying_Price": 4998,
    "Selling_Price": 10032,
    "silver_profit": 5034,
    "Ratio": 0.5017942583732058
  },
  {
    "itemId": "T3_SHOES_LEATHER_SET1",
    "itemName": "Journeyman's Mercenary Shoes",
    "itemTag": "@ITEMS_T3_SHOES_LEATHER_SET1",
    "selectedMarket": "Martlock",
    "otherMarket": "Black Market",
    "Buying_Price": 624,
    "Selling_Price": 1242,
    "silver_profit": 618,
    "Ratio": 0.4975845410628019
  },
  {
    "itemId": "T4_SHOES_PLATE_UNDEAD",
    "itemName": "Adept's Graveguard Boots",
    "itemTag": "@ITEMS_T4_SHOES_PLATE_UNDEAD",
    "selectedMarket": "Martlock",
    "otherMarket": "Black Market",
    "Buying_Price": 1838,
    "Selling_Price": 3648,
    "silver_profit": 1810,
    "Ratio": 0.4961622807017544
  },
  {
    "itemId": "T7_HEAD_PLATE_SET3",
    "itemName": "Grandmaster's Guardian Helmet",
    "itemTag": "@ITEMS_T7_HEAD_PLATE_SET3",
    "selectedMarket": "Martlock",
    "otherMarket": "Black Market",
    "Buying_Price": 25547,
    "Selling_Price": 49640,
    "silver_profit": 24093,
    "Ratio": 0.4853545527800161
  },
  {
    "itemId": "T6_MAIN_HAMMER",
    "itemName": "Master's Hammer",
    "itemTag": "@ITEMS_T6_MAIN_HAMMER",
    "selectedMarket": "Martlock",
    "otherMarket": "Black Market",
    "Buying_Price": 20988,
    "Selling_Price": 40515,
    "silver_profit": 19527,
    "Ratio": 0.48196964087375044
  },
  {
    "itemId": "T3_BAG",
    "itemName": "Journeyman's Bag",
    "itemTag": "@ITEMS_T3_BAG",
    "selectedMarket": "Martlock",
    "otherMarket": "Black Market",
    "Buying_Price": 1463,
    "Selling_Price": 2821,
    "silver_profit": 1358,
    "Ratio": 0.4813895781637717
  },
  {
    "itemId": "T4_HEAD_PLATE_UNDEAD",
    "itemName": "Adept's Graveguard Helmet",
    "itemTag": "@ITEMS_T4_HEAD_PLATE_UNDEAD",
    "selectedMarket": "Martlock",
    "otherMarket": "Black Market",
    "Buying_Price": 1830,
    "Selling_Price": 3420,
    "silver_profit": 1590,
    "Ratio": 0.4649122807017544
  },
  {
    "itemId": "T4_OFF_TORCH",
    "itemName": "Adept's Torch",
    "itemTag": "@ITEMS_T4_OFF_TORCH",
    "selectedMarket": "Martlock",
    "otherMarket": "Black Market",
    "Buying_Price": 539,
    "Selling_Price": 1001,
    "silver_profit": 462,
    "Ratio": 0.46153846153846156
  },
  {
    "itemId": "T5_SHOES_PLATE_SET2",
    "itemName": "Expert's Knight Boots",
    "itemTag": "@ITEMS_T5_SHOES_PLATE_SET2",
    "selectedMarket": "Martlock",
    "otherMarket": "Black Market",
    "Buying_Price": 1986,
    "Selling_Price": 3660,
    "silver_profit": 1674,
    "Ratio": 0.45737704918032784
  },
  {
    "itemId": "T4_ARMOR_LEATHER_SET1",
    "itemName": "Adept's Mercenary Jacket",
    "itemTag": "@ITEMS_T4_ARMOR_LEATHER_SET1",
    "selectedMarket": "Martlock",
    "otherMarket": "Black Market",
    "Buying_Price": 895,
    "Selling_Price": 1647,
    "silver_profit": 752,
    "Ratio": 0.45658773527625984
  },
  {
    "itemId": "T3_HEAD_PLATE_SET1",
    "itemName": "Journeyman's Soldier Helmet",
    "itemTag": "@ITEMS_T3_HEAD_PLATE_SET1",
    "selectedMarket": "Martlock",
    "otherMarket": "Black Market",
    "Buying_Price": 502,
    "Selling_Price": 920,
    "silver_profit": 418,
    "Ratio": 0.4543478260869565
  },
  {
    "itemId": "T4_ARMOR_CLOTH_SET2",
    "itemName": "Adept's Cleric Robe",
    "itemTag": "@ITEMS_T4_ARMOR_CLOTH_SET2",
    "selectedMarket": "Martlock",
    "otherMarket": "Black Market",
    "Buying_Price": 999,
    "Selling_Price": 1830,
    "silver_profit": 831,
    "Ratio": 0.4540983606557377
  },
  {
    "itemId": "T4_ARMOR_LEATHER_MORGANA",
    "itemName": "Adept's Stalker Jacket",
    "itemTag": "@ITEMS_T4_ARMOR_LEATHER_MORGANA",
    "selectedMarket": "Martlock",
    "otherMarket": "Black Market",
    "Buying_Price": 1999,
    "Selling_Price": 3648,
    "silver_profit": 1649,
    "Ratio": 0.45202850877192985
  },
  {
    "itemId": "T4_HEAD_CLOTH_KEEPER",
    "itemName": "Adept's Druid Cowl",
    "itemTag": "@ITEMS_T4_HEAD_CLOTH_KEEPER",
    "selectedMarket": "Martlock",
    "otherMarket": "Black Market",
    "Buying_Price": 2990,
    "Selling_Price": 5358,
    "silver_profit": 2368,
    "Ratio": 0.4419559537140724
  },
  {
    "itemId": "T5_HEAD_PLATE_SET2",
    "itemName": "Expert's Knight Helmet",
    "itemTag": "@ITEMS_T5_HEAD_PLATE_SET2",
    "selectedMarket": "Martlock",
    "otherMarket": "Black Market",
    "Buying_Price": 1947,
    "Selling_Price": 3477,
    "silver_profit": 1530,
    "Ratio": 0.4400345125107852
  },
  {
    "itemId": "T5_SHOES_PLATE_SET3",
    "itemName": "Expert's Guardian Boots",
    "itemTag": "@ITEMS_T5_SHOES_PLATE_SET3",
    "selectedMarket": "Martlock",
    "otherMarket": "Black Market",
    "Buying_Price": 2182,
    "Selling_Price": 3843,
    "silver_profit": 1661,
    "Ratio": 0.4322144158209732
  },
  {
    "itemId": "T5_2H_FIRESTAFF",
    "itemName": "Expert's Great Fire Staff",
    "itemTag": "@ITEMS_T5_2H_FIRESTAFF",
    "selectedMarket": "Martlock",
    "otherMarket": "Black Market",
    "Buying_Price": 8769,
    "Selling_Price": 15330,
    "silver_profit": 6561,
    "Ratio": 0.4279843444227006
  },
  {
    "itemId": "T5_ARMOR_PLATE_SET2@1",
    "itemName": "Expert's Knight Armor",
    "itemTag": "@ITEMS_T5_ARMOR_PLATE_SET2",
    "selectedMarket": "Martlock",
    "otherMarket": "Black Market",
    "Buying_Price": 11488,
    "Selling_Price": 19710,
    "silver_profit": 8222,
    "Ratio": 0.4171486555048199
  },
  {
    "itemId": "T6_HEAD_PLATE_SET2@1",
    "itemName": "Master's Knight Helmet",
    "itemTag": "@ITEMS_T6_HEAD_PLATE_SET2",
    "selectedMarket": "Martlock",
    "otherMarket": "Black Market",
    "Buying_Price": 17991,
    "Selling_Price": 30660,
    "silver_profit": 12669,
    "Ratio": 0.4132093933463796
  },
  {
    "itemId": "T5_2H_KNUCKLES_SET2",
    "itemName": "Expert's Battle Bracers",
    "itemTag": "@ITEMS_T5_2H_KNUCKLES_SET2",
    "selectedMarket": "Martlock",
    "otherMarket": "Black Market",
    "Buying_Price": 15400,
    "Selling_Price": 26000,
    "silver_profit": 10600,
    "Ratio": 0.4076923076923077
  },
  {
    "itemId": "T5_2H_CROSSBOW@1",
    "itemName": "Expert's Crossbow",
    "itemTag": "@ITEMS_T5_2H_CROSSBOW",
    "selectedMarket": "Martlock",
    "otherMarket": "Black Market",
    "Buying_Price": 19998,
    "Selling_Price": 33580,
    "silver_profit": 13582,
    "Ratio": 0.40446694460988686
  },
  {
    "itemId": "T5_SHOES_CLOTH_SET1",
    "itemName": "Expert's Scholar Sandals",
    "itemTag": "@ITEMS_T5_SHOES_CLOTH_SET1",
    "selectedMarket": "Martlock",
    "otherMarket": "Black Market",
    "Buying_Price": 2299,
    "Selling_Price": 3843,
    "silver_profit": 1544,
    "Ratio": 0.40176945094977884
  },
  {
    "itemId": "T5_HEAD_CLOTH_SET1",
    "itemName": "Expert's Scholar Cowl",
    "itemTag": "@ITEMS_T5_HEAD_CLOTH_SET1",
    "selectedMarket": "Martlock",
    "otherMarket": "Black Market",
    "Buying_Price": 2199,
    "Selling_Price": 3660,
    "silver_profit": 1461,
    "Ratio": 0.39918032786885244
  },
  {
    "itemId": "T5_MAIN_FIRESTAFF",
    "itemName": "Expert's Fire Staff",
    "itemTag": "@ITEMS_T5_MAIN_FIRESTAFF",
    "selectedMarket": "Martlock",
    "otherMarket": "Black Market",
    "Buying_Price": 5981,
    "Selling_Price": 9864,
    "silver_profit": 3883,
    "Ratio": 0.3936536901865369
  },
  {
    "itemId": "T5_ARMOR_PLATE_UNDEAD",
    "itemName": "Expert's Graveguard Armor",
    "itemTag": "@ITEMS_T5_ARMOR_PLATE_UNDEAD",
    "selectedMarket": "Martlock",
    "otherMarket": "Black Market",
    "Buying_Price": 7942,
    "Selling_Price": 12768,
    "silver_profit": 4826,
    "Ratio": 0.37797619047619047
  },
  {
    "itemId": "T3_2H_KNUCKLES_SET1",
    "itemName": "Journeyman's Brawler Gloves",
    "itemTag": "@ITEMS_T3_2H_KNUCKLES_SET1",
    "selectedMarket": "Martlock",
    "otherMarket": "Black Market",
    "Buying_Price": 2619,
    "Selling_Price": 4209,
    "silver_profit": 1590,
    "Ratio": 0.37776193870277974
  },
  {
    "itemId": "T5_2H_HARPOON_HELL",
    "itemName": "Expert's Spirithunter",
    "itemTag": "@ITEMS_T5_2H_HARPOON_HELL",
    "selectedMarket": "Martlock",
    "otherMarket": "Black Market",
    "Buying_Price": 13730,
    "Selling_Price": 21726,
    "silver_profit": 7996,
    "Ratio": 0.36803829513025865
  },
  {
    "itemId": "T4_HEAD_CLOTH_SET1",
    "itemName": "Adept's Scholar Cowl",
    "itemTag": "@ITEMS_T4_HEAD_CLOTH_SET1",
    "selectedMarket": "Martlock",
    "otherMarket": "Black Market",
    "Buying_Price": 580,
    "Selling_Price": 910,
    "silver_profit": 330,
    "Ratio": 0.3626373626373626
  },
  {
    "itemId": "T4_MAIN_AXE",
    "itemName": "Adept's Battleaxe",
    "itemTag": "@ITEMS_T4_MAIN_AXE",
    "selectedMarket": "Martlock",
    "otherMarket": "Black Market",
    "Buying_Price": 1230,
    "Selling_Price": 1918,
    "silver_profit": 688,
    "Ratio": 0.3587069864442127
  },
  {
    "itemId": "T5_ARMOR_CLOTH_SET1",
    "itemName": "Expert's Scholar Robe",
    "itemTag": "@ITEMS_T5_ARMOR_CLOTH_SET1",
    "selectedMarket": "Martlock",
    "otherMarket": "Black Market",
    "Buying_Price": 4000,
    "Selling_Price": 6205,
    "silver_profit": 2205,
    "Ratio": 0.3553585817888799
  },
  {
    "itemId": "T5_ARMOR_PLATE_SET1",
    "itemName": "Expert's Soldier Armor",
    "itemTag": "@ITEMS_T5_ARMOR_PLATE_SET1",
    "selectedMarket": "Martlock",
    "otherMarket": "Black Market",
    "Buying_Price": 5187,
    "Selling_Price": 8030,
    "silver_profit": 2843,
    "Ratio": 0.3540473225404732
  },
  {
    "itemId": "T5_2H_DIVINESTAFF",
    "itemName": "Expert's Divine Staff",
    "itemTag": "@ITEMS_T5_2H_DIVINESTAFF",
    "selectedMarket": "Martlock",
    "otherMarket": "Black Market",
    "Buying_Price": 8999,
    "Selling_Price": 13870,
    "silver_profit": 4871,
    "Ratio": 0.3511896178803172
  },
  {
    "itemId": "T4_CAPE",
    "itemName": "Adept's Cape",
    "itemTag": "@ITEMS_T4_CAPE",
    "selectedMarket": "Martlock",
    "otherMarket": "Black Market",
    "Buying_Price": 1066,
    "Selling_Price": 1638,
    "silver_profit": 572,
    "Ratio": 0.3492063492063492
  },
  {
    "itemId": "T5_2H_DAGGERPAIR",
    "itemName": "Expert's Dagger Pair",
    "itemTag": "@ITEMS_T5_2H_DAGGERPAIR",
    "selectedMarket": "Martlock",
    "otherMarket": "Black Market",
    "Buying_Price": 14785,
    "Selling_Price": 22630,
    "silver_profit": 7845,
    "Ratio": 0.3466637207247017
  },
  {
    "itemId": "T4_SHOES_LEATHER_MORGANA",
    "itemName": "Adept's Stalker Shoes",
    "itemTag": "@ITEMS_T4_SHOES_LEATHER_MORGANA",
    "selectedMarket": "Martlock",
    "otherMarket": "Black Market",
    "Buying_Price": 894,
    "Selling_Price": 1368,
    "silver_profit": 474,
    "Ratio": 0.34649122807017546
  },
  {
    "itemId": "T4_BAG_INSIGHT",
    "itemName": "Adept's Satchel of Insight",
    "itemTag": "@ITEMS_T4_BAG_INSIGHT",
    "selectedMarket": "Martlock",
    "otherMarket": "Black Market",
    "Buying_Price": 14490,
    "Selling_Price": 22143,
    "silver_profit": 7653,
    "Ratio": 0.3456171250508061
  },
  {
    "itemId": "T5_SHOES_CLOTH_SET2",
    "itemName": "Expert's Cleric Sandals",
    "itemTag": "@ITEMS_T5_SHOES_CLOTH_SET2",
    "selectedMarket": "Martlock",
    "otherMarket": "Black Market",
    "Buying_Price": 2533,
    "Selling_Price": 3843,
    "silver_profit": 1310,
    "Ratio": 0.34087952120739007
  },
  {
    "itemId": "T5_HEAD_LEATHER_SET2",
    "itemName": "Expert's Hunter Hood",
    "itemTag": "@ITEMS_T5_HEAD_LEATHER_SET2",
    "selectedMarket": "Martlock",
    "otherMarket": "Black Market",
    "Buying_Price": 3997,
    "Selling_Price": 6039,
    "silver_profit": 2042,
    "Ratio": 0.33813545288955127
  },
  {
    "itemId": "T5_ARMOR_CLOTH_SET2",
    "itemName": "Expert's Cleric Robe",
    "itemTag": "@ITEMS_T5_ARMOR_CLOTH_SET2",
    "selectedMarket": "Martlock",
    "otherMarket": "Black Market",
    "Buying_Price": 4640,
    "Selling_Price": 6935,
    "silver_profit": 2295,
    "Ratio": 0.330930064888248
  },
  {
    "itemId": "T5_2H_WARBOW",
    "itemName": "Expert's Warbow",
    "itemTag": "@ITEMS_T5_2H_WARBOW",
    "selectedMarket": "Martlock",
    "otherMarket": "Black Market",
    "Buying_Price": 5874,
    "Selling_Price": 8760,
    "silver_profit": 2886,
    "Ratio": 0.32945205479452055
  },
  {
    "itemId": "T5_2H_LONGBOW",
    "itemName": "Expert's Longbow",
    "itemTag": "@ITEMS_T5_2H_LONGBOW",
    "selectedMarket": "Martlock",
    "otherMarket": "Black Market",
    "Buying_Price": 4899,
    "Selling_Price": 7300,
    "silver_profit": 2401,
    "Ratio": 0.3289041095890411
  },
  {
    "itemId": "T4_SHOES_LEATHER_SET2",
    "itemName": "Adept's Hunter Shoes",
    "itemTag": "@ITEMS_T4_SHOES_LEATHER_SET2",
    "selectedMarket": "Martlock",
    "otherMarket": "Black Market",
    "Buying_Price": 502,
    "Selling_Price": 728,
    "silver_profit": 226,
    "Ratio": 0.31043956043956045
  },
  {
    "itemId": "T5_HEAD_CLOTH_SET2",
    "itemName": "Expert's Cleric Cowl",
    "itemTag": "@ITEMS_T5_HEAD_CLOTH_SET2",
    "selectedMarket": "Martlock",
    "otherMarket": "Black Market",
    "Buying_Price": 2661,
    "Selling_Price": 3843,
    "silver_profit": 1182,
    "Ratio": 0.3075722092115535
  },
  {
    "itemId": "T5_ARMOR_PLATE_SET3",
    "itemName": "Expert's Guardian Armor",
    "itemTag": "@ITEMS_T5_ARMOR_PLATE_SET3",
    "selectedMarket": "Martlock",
    "otherMarket": "Black Market",
    "Buying_Price": 5361,
    "Selling_Price": 7665,
    "silver_profit": 2304,
    "Ratio": 0.300587084148728
  },
  {
    "itemId": "T5_ARMOR_LEATHER_SET1",
    "itemName": "Expert's Mercenary Jacket",
    "itemTag": "@ITEMS_T5_ARMOR_LEATHER_SET1",
    "selectedMarket": "Martlock",
    "otherMarket": "Black Market",
    "Buying_Price": 6962,
    "Selling_Price": 9855,
    "silver_profit": 2893,
    "Ratio": 0.29355657026889903
  },
  {
    "itemId": "T5_ARMOR_PLATE_SET2",
    "itemName": "Expert's Knight Armor",
    "itemTag": "@ITEMS_T5_ARMOR_PLATE_SET2",
    "selectedMarket": "Martlock",
    "otherMarket": "Black Market",
    "Buying_Price": 5442,
    "Selling_Price": 7665,
    "silver_profit": 2223,
    "Ratio": 0.2900195694716243
  },
  {
    "itemId": "T7_HEAD_PLATE_SET1",
    "itemName": "Grandmaster's Soldier Helmet",
    "itemTag": "@ITEMS_T7_HEAD_PLATE_SET1",
    "selectedMarket": "Martlock",
    "otherMarket": "Black Market",
    "Buying_Price": 26983,
    "Selling_Price": 37960,
    "silver_profit": 10977,
    "Ratio": 0.289172813487882
  },
  {
    "itemId": "T5_MAIN_DAGGER",
    "itemName": "Expert's Dagger",
    "itemTag": "@ITEMS_T5_MAIN_DAGGER",
    "selectedMarket": "Martlock",
    "otherMarket": "Black Market",
    "Buying_Price": 8809,
    "Selling_Price": 12056,
    "silver_profit": 3247,
    "Ratio": 0.26932647644326474
  },
  {
    "itemId": "T7_OFF_BOOK",
    "itemName": "Grandmaster's Tome of Spells",
    "itemTag": "@ITEMS_T7_OFF_BOOK",
    "selectedMarket": "Martlock",
    "otherMarket": "Black Market",
    "Buying_Price": 31148,
    "Selling_Price": 42340,
    "silver_profit": 11192,
    "Ratio": 0.2643363249881908
  },
  {
    "itemId": "T5_SHOES_LEATHER_SET1@2",
    "itemName": "Expert's Mercenary Shoes",
    "itemTag": "@ITEMS_T5_SHOES_LEATHER_SET1",
    "selectedMarket": "Martlock",
    "otherMarket": "Black Market",
    "Buying_Price": 19900,
    "Selling_Price": 27010,
    "silver_profit": 7110,
    "Ratio": 0.26323583857830435
  },
  {
    "itemId": "T5_OFF_TORCH@1",
    "itemName": "Expert's Torch",
    "itemTag": "@ITEMS_T5_OFF_TORCH",
    "selectedMarket": "Martlock",
    "otherMarket": "Black Market",
    "Buying_Price": 5686,
    "Selling_Price": 7665,
    "silver_profit": 1979,
    "Ratio": 0.25818656229615133
  },
  {
    "itemId": "T5_ARMOR_LEATHER_SET3@1",
    "itemName": "Expert's Assassin Jacket",
    "itemTag": "@ITEMS_T5_ARMOR_LEATHER_SET3",
    "selectedMarket": "Martlock",
    "otherMarket": "Black Market",
    "Buying_Price": 12499,
    "Selling_Price": 16790,
    "silver_profit": 4291,
    "Ratio": 0.25556879094699225
  },
  {
    "itemId": "T4_HEAD_LEATHER_HELL@2",
    "itemName": "Adept's Hellion Hood",
    "itemTag": "@ITEMS_T4_HEAD_LEATHER_HELL",
    "selectedMarket": "Martlock",
    "otherMarket": "Black Market",
    "Buying_Price": 6479,
    "Selling_Price": 8680,
    "silver_profit": 2201,
    "Ratio": 0.25357142857142856
  },
  {
    "itemId": "T5_SHOES_PLATE_SET3@1",
    "itemName": "Expert's Guardian Boots",
    "itemTag": "@ITEMS_T5_SHOES_PLATE_SET3",
    "selectedMarket": "Martlock",
    "otherMarket": "Black Market",
    "Buying_Price": 5996,
    "Selling_Price": 8030,
    "silver_profit": 2034,
    "Ratio": 0.25330012453300127
  },
  {
    "itemId": "T5_CAPEITEM_FW_BRIDGEWATCH@1",
    "itemName": "Expert's Bridgewatch Cape",
    "itemTag": "@ITEMS_T5_CAPEITEM_FW_BRIDGEWATCH",
    "selectedMarket": "Martlock",
    "otherMarket": "Black Market",
    "Buying_Price": 79996,
    "Selling_Price": 106860,
    "silver_profit": 26864,
    "Ratio": 0.2513943477447127
  },
  {
    "itemId": "T5_ARMOR_LEATHER_SET3",
    "itemName": "Expert's Assassin Jacket",
    "itemTag": "@ITEMS_T5_ARMOR_LEATHER_SET3",
    "selectedMarket": "Martlock",
    "otherMarket": "Black Market",
    "Buying_Price": 6575,
    "Selling_Price": 8760,
    "silver_profit": 2185,
    "Ratio": 0.24942922374429224
  },
  {
    "itemId": "T7_HEAD_CLOTH_SET3",
    "itemName": "Grandmaster's Mage Cowl",
    "itemTag": "@ITEMS_T7_HEAD_CLOTH_SET3",
    "selectedMarket": "Martlock",
    "otherMarket": "Black Market",
    "Buying_Price": 26942,
    "Selling_Price": 35770,
    "silver_profit": 8828,
    "Ratio": 0.24679899357003074
  },
  {
    "itemId": "T7_2H_CURSEDSTAFF",
    "itemName": "Grandmaster's Great Cursed Staff",
    "itemTag": "@ITEMS_T7_2H_CURSEDSTAFF",
    "selectedMarket": "Martlock",
    "otherMarket": "Black Market",
    "Buying_Price": 87999,
    "Selling_Price": 116800,
    "silver_profit": 28801,
    "Ratio": 0.24658390410958905
  },
  {
    "itemId": "T6_SHOES_LEATHER_SET3",
    "itemName": "Master's Assassin Shoes",
    "itemTag": "@ITEMS_T6_SHOES_LEATHER_SET3",
    "selectedMarket": "Martlock",
    "otherMarket": "Black Market",
    "Buying_Price": 12955,
    "Selling_Price": 17155,
    "silver_profit": 4200,
    "Ratio": 0.24482658117167005
  },
  {
    "itemId": "T6_ARMOR_PLATE_UNDEAD",
    "itemName": "Master's Graveguard Armor",
    "itemTag": "@ITEMS_T6_ARMOR_PLATE_UNDEAD",
    "selectedMarket": "Martlock",
    "otherMarket": "Black Market",
    "Buying_Price": 24955,
    "Selling_Price": 32868,
    "silver_profit": 7913,
    "Ratio": 0.2407508823171474
  },
  {
    "itemId": "T7_SHOES_PLATE_SET1",
    "itemName": "Grandmaster's Soldier Boots",
    "itemTag": "@ITEMS_T7_SHOES_PLATE_SET1",
    "selectedMarket": "Martlock",
    "otherMarket": "Black Market",
    "Buying_Price": 19993,
    "Selling_Price": 26280,
    "silver_profit": 6287,
    "Ratio": 0.23923135464231354
  },
  {
    "itemId": "T7_2H_FROSTSTAFF",
    "itemName": "Grandmaster's Great Frost Staff",
    "itemTag": "@ITEMS_T7_2H_FROSTSTAFF",
    "selectedMarket": "Martlock",
    "otherMarket": "Black Market",
    "Buying_Price": 79995,
    "Selling_Price": 105120,
    "silver_profit": 25125,
    "Ratio": 0.23901255707762556
  },
  {
    "itemId": "T7_2H_TOOL_HAMMER",
    "itemName": "Grandmaster's Stone Hammer",
    "itemTag": "@ITEMS_T7_2H_TOOL_HAMMER",
    "selectedMarket": "Martlock",
    "otherMarket": "Black Market",
    "Buying_Price": 43485,
    "Selling_Price": 56940,
    "silver_profit": 13455,
    "Ratio": 0.2363013698630137
  },
  {
    "itemId": "T6_SHOES_CLOTH_SET2",
    "itemName": "Master's Cleric Sandals",
    "itemTag": "@ITEMS_T6_SHOES_CLOTH_SET2",
    "selectedMarket": "Martlock",
    "otherMarket": "Black Market",
    "Buying_Price": 8394,
    "Selling_Price": 10950,
    "silver_profit": 2556,
    "Ratio": 0.23342465753424657
  },
  {
    "itemId": "T7_HEAD_CLOTH_SET3@1",
    "itemName": "Grandmaster's Mage Cowl",
    "itemTag": "@ITEMS_T7_HEAD_CLOTH_SET3",
    "selectedMarket": "Martlock",
    "otherMarket": "Black Market",
    "Buying_Price": 62898,
    "Selling_Price": 81760,
    "silver_profit": 18862,
    "Ratio": 0.2306996086105675
  },
  {
    "itemId": "T5_SHOES_PLATE_SET2@1",
    "itemName": "Expert's Knight Boots",
    "itemTag": "@ITEMS_T5_SHOES_PLATE_SET2",
    "selectedMarket": "Martlock",
    "otherMarket": "Black Market",
    "Buying_Price": 6200,
    "Selling_Price": 8030,
    "silver_profit": 1830,
    "Ratio": 0.22789539227895392
  },
  {
    "itemId": "T4_ARMOR_PLATE_SET2",
    "itemName": "Adept's Knight Armor",
    "itemTag": "@ITEMS_T4_ARMOR_PLATE_SET2",
    "selectedMarket": "Martlock",
    "otherMarket": "Black Market",
    "Buying_Price": 848,
    "Selling_Price": 1098,
    "silver_profit": 250,
    "Ratio": 0.22768670309653916
  },
  {
    "itemId": "T7_SHOES_CLOTH_SET2",
    "itemName": "Grandmaster's Cleric Sandals",
    "itemTag": "@ITEMS_T7_SHOES_CLOTH_SET2",
    "selectedMarket": "Martlock",
    "otherMarket": "Black Market",
    "Buying_Price": 28276,
    "Selling_Price": 36500,
    "silver_profit": 8224,
    "Ratio": 0.2253150684931507
  },
  {
    "itemId": "T3_HEAD_CLOTH_SET1",
    "itemName": "Journeyman's Scholar Cowl",
    "itemTag": "@ITEMS_T3_HEAD_CLOTH_SET1",
    "selectedMarket": "Martlock",
    "otherMarket": "Black Market",
    "Buying_Price": 606,
    "Selling_Price": 782,
    "silver_profit": 176,
    "Ratio": 0.22506393861892582
  },
  {
    "itemId": "T7_SHOES_CLOTH_SET1",
    "itemName": "Grandmaster's Scholar Sandals",
    "itemTag": "@ITEMS_T7_SHOES_CLOTH_SET1",
    "selectedMarket": "Martlock",
    "otherMarket": "Black Market",
    "Buying_Price": 25470,
    "Selling_Price": 32850,
    "silver_profit": 7380,
    "Ratio": 0.22465753424657534
  },
  {
    "itemId": "T7_ARMOR_CLOTH_SET3",
    "itemName": "Grandmaster's Mage Robe",
    "itemTag": "@ITEMS_T7_ARMOR_CLOTH_SET3",
    "selectedMarket": "Martlock",
    "otherMarket": "Black Market",
    "Buying_Price": 50942,
    "Selling_Price": 65700,
    "silver_profit": 14758,
    "Ratio": 0.22462709284627091
  },
  {
    "itemId": "T6_HEAD_PLATE_SET2",
    "itemName": "Master's Knight Helmet",
    "itemTag": "@ITEMS_T6_HEAD_PLATE_SET2",
    "selectedMarket": "Martlock",
    "otherMarket": "Black Market",
    "Buying_Price": 8943,
    "Selling_Price": 11315,
    "silver_profit": 2372,
    "Ratio": 0.20963323022536456
  },
  {
    "itemId": "T7_ARMOR_LEATHER_SET1",
    "itemName": "Grandmaster's Mercenary Jacket",
    "itemTag": "@ITEMS_T7_ARMOR_LEATHER_SET1",
    "selectedMarket": "Martlock",
    "otherMarket": "Black Market",
    "Buying_Price": 87998,
    "Selling_Price": 110960,
    "silver_profit": 22962,
    "Ratio": 0.20693943763518385
  },
  {
    "itemId": "T7_2H_BOW",
    "itemName": "Grandmaster's Bow",
    "itemTag": "@ITEMS_T7_2H_BOW",
    "selectedMarket": "Martlock",
    "otherMarket": "Black Market",
    "Buying_Price": 64968,
    "Selling_Price": 81760,
    "silver_profit": 16792,
    "Ratio": 0.2053816046966732
  },
  {
    "itemId": "T6_SHOES_LEATHER_SET2",
    "itemName": "Master's Hunter Shoes",
    "itemTag": "@ITEMS_T6_SHOES_LEATHER_SET2",
    "selectedMarket": "Martlock",
    "otherMarket": "Black Market",
    "Buying_Price": 12183,
    "Selling_Price": 15330,
    "silver_profit": 3147,
    "Ratio": 0.20528375733855186
  },
  {
    "itemId": "T5_2H_DEMONICSTAFF",
    "itemName": "Expert's Demonic Staff",
    "itemTag": "@ITEMS_T5_2H_DEMONICSTAFF",
    "selectedMarket": "Martlock",
    "otherMarket": "Black Market",
    "Buying_Price": 10472,
    "Selling_Price": 13140,
    "silver_profit": 2668,
    "Ratio": 0.2030441400304414
  },
  {
    "itemId": "T4_BAG",
    "itemName": "Adept's Bag",
    "itemTag": "@ITEMS_T4_BAG",
    "selectedMarket": "Martlock",
    "otherMarket": "Black Market",
    "Buying_Price": 2190,
    "Selling_Price": 2745,
    "silver_profit": 555,
    "Ratio": 0.20218579234972678
  },
  {
    "itemId": "T6_ARMOR_LEATHER_SET2",
    "itemName": "Master's Hunter Jacket",
    "itemTag": "@ITEMS_T6_ARMOR_LEATHER_SET2",
    "selectedMarket": "Martlock",
    "otherMarket": "Black Market",
    "Buying_Price": 27999,
    "Selling_Price": 35040,
    "silver_profit": 7041,
    "Ratio": 0.2009417808219178
  },
  {
    "itemId": "T6_ARMOR_CLOTH_SET3",
    "itemName": "Master's Mage Robe",
    "itemTag": "@ITEMS_T6_ARMOR_CLOTH_SET3",
    "selectedMarket": "Martlock",
    "otherMarket": "Black Market",
    "Buying_Price": 16382,
    "Selling_Price": 20440,
    "silver_profit": 4058,
    "Ratio": 0.19853228962818004
  },
  {
    "itemId": "T6_HEAD_LEATHER_MORGANA",
    "itemName": "Master's Stalker Hood",
    "itemTag": "@ITEMS_T6_HEAD_LEATHER_MORGANA",
    "selectedMarket": "Martlock",
    "otherMarket": "Black Market",
    "Buying_Price": 21975,
    "Selling_Price": 27360,
    "silver_profit": 5385,
    "Ratio": 0.19682017543859648
  },
  {
    "itemId": "T7_ARMOR_PLATE_SET2",
    "itemName": "Grandmaster's Knight Armor",
    "itemTag": "@ITEMS_T7_ARMOR_PLATE_SET2",
    "selectedMarket": "Martlock",
    "otherMarket": "Black Market",
    "Buying_Price": 38942,
    "Selling_Price": 48180,
    "silver_profit": 9238,
    "Ratio": 0.1917393109173931
  },
  {
    "itemId": "T5_2H_ARCANESTAFF@1",
    "itemName": "Expert's Great Arcane Staff",
    "itemTag": "@ITEMS_T5_2H_ARCANESTAFF",
    "selectedMarket": "Martlock",
    "otherMarket": "Black Market",
    "Buying_Price": 18996,
    "Selling_Price": 23360,
    "silver_profit": 4364,
    "Ratio": 0.1868150684931507
  },
  {
    "itemId": "T4_2H_ARCANESTAFF_HELL",
    "itemName": "Adept's Occult Staff",
    "itemTag": "@ITEMS_T4_2H_ARCANESTAFF_HELL",
    "selectedMarket": "Martlock",
    "otherMarket": "Black Market",
    "Buying_Price": 7949,
    "Selling_Price": 9585,
    "silver_profit": 1636,
    "Ratio": 0.17068335941575377
  },
  {
    "itemId": "T5_BAG@1",
    "itemName": "Expert's Bag",
    "itemTag": "@ITEMS_T5_BAG",
    "selectedMarket": "Martlock",
    "otherMarket": "Black Market",
    "Buying_Price": 16985,
    "Selling_Price": 20440,
    "silver_profit": 3455,
    "Ratio": 0.16903131115459882
  },
  {
    "itemId": "T7_SHOES_LEATHER_SET3",
    "itemName": "Grandmaster's Assassin Shoes",
    "itemTag": "@ITEMS_T7_SHOES_LEATHER_SET3",
    "selectedMarket": "Martlock",
    "otherMarket": "Black Market",
    "Buying_Price": 40388,
    "Selling_Price": 48180,
    "silver_profit": 7792,
    "Ratio": 0.16172685761726857
  },
  {
    "itemId": "T6_ARMOR_CLOTH_SET1",
    "itemName": "Master's Scholar Robe",
    "itemTag": "@ITEMS_T6_ARMOR_CLOTH_SET1",
    "selectedMarket": "Martlock",
    "otherMarket": "Black Market",
    "Buying_Price": 17996,
    "Selling_Price": 21170,
    "silver_profit": 3174,
    "Ratio": 0.14992914501653282
  },
  {
    "itemId": "T5_BAG@2",
    "itemName": "Expert's Bag",
    "itemTag": "@ITEMS_T5_BAG",
    "selectedMarket": "Martlock",
    "otherMarket": "Black Market",
    "Buying_Price": 60996,
    "Selling_Price": 71540,
    "silver_profit": 10544,
    "Ratio": 0.14738607771875872
  },
  {
    "itemId": "T7_ARMOR_CLOTH_SET2",
    "itemName": "Grandmaster's Cleric Robe",
    "itemTag": "@ITEMS_T7_ARMOR_CLOTH_SET2",
    "selectedMarket": "Martlock",
    "otherMarket": "Black Market",
    "Buying_Price": 59989,
    "Selling_Price": 70080,
    "silver_profit": 10091,
    "Ratio": 0.1439925799086758
  },
  {
    "itemId": "T7_ARMOR_LEATHER_SET2",
    "itemName": "Grandmaster's Hunter Jacket",
    "itemTag": "@ITEMS_T7_ARMOR_LEATHER_SET2",
    "selectedMarket": "Martlock",
    "otherMarket": "Black Market",
    "Buying_Price": 93997,
    "Selling_Price": 109500,
    "silver_profit": 15503,
    "Ratio": 0.1415799086757991
  },
  {
    "itemId": "T5_BAG_INSIGHT",
    "itemName": "Expert's Satchel of Insight",
    "itemTag": "@ITEMS_T5_BAG_INSIGHT",
    "selectedMarket": "Martlock",
    "otherMarket": "Black Market",
    "Buying_Price": 26410,
    "Selling_Price": 30295,
    "silver_profit": 3885,
    "Ratio": 0.12823898333058262
  },
  {
    "itemId": "T6_ARMOR_LEATHER_SET3",
    "itemName": "Master's Assassin Jacket",
    "itemTag": "@ITEMS_T6_ARMOR_LEATHER_SET3",
    "selectedMarket": "Martlock",
    "otherMarket": "Black Market",
    "Buying_Price": 29297,
    "Selling_Price": 33580,
    "silver_profit": 4283,
    "Ratio": 0.1275461584276355
  },
  {
    "itemId": "T7_2H_MACE",
    "itemName": "Grandmaster's Heavy Mace",
    "itemTag": "@ITEMS_T7_2H_MACE",
    "selectedMarket": "Martlock",
    "otherMarket": "Black Market",
    "Buying_Price": 114997,
    "Selling_Price": 131400,
    "silver_profit": 16403,
    "Ratio": 0.12483257229832573
  },
  {
    "itemId": "T5_BAG_INSIGHT@1",
    "itemName": "Expert's Satchel of Insight",
    "itemTag": "@ITEMS_T5_BAG_INSIGHT",
    "selectedMarket": "Martlock",
    "otherMarket": "Black Market",
    "Buying_Price": 33272,
    "Selling_Price": 37960,
    "silver_profit": 4688,
    "Ratio": 0.12349841938883034
  },
  {
    "itemId": "T7_HEAD_LEATHER_SET1",
    "itemName": "Grandmaster's Mercenary Hood",
    "itemTag": "@ITEMS_T7_HEAD_LEATHER_SET1",
    "selectedMarket": "Martlock",
    "otherMarket": "Black Market",
    "Buying_Price": 38423,
    "Selling_Price": 43800,
    "silver_profit": 5377,
    "Ratio": 0.12276255707762557
  },
  {
    "itemId": "T7_BAG",
    "itemName": "Grandmaster's Bag",
    "itemTag": "@ITEMS_T7_BAG",
    "selectedMarket": "Martlock",
    "otherMarket": "Black Market",
    "Buying_Price": 107692,
    "Selling_Price": 122640,
    "silver_profit": 14948,
    "Ratio": 0.12188519243313764
  },
  {
    "itemId": "T4_HEAD_LEATHER_SET3@1",
    "itemName": "Adept's Assassin Hood",
    "itemTag": "@ITEMS_T4_HEAD_LEATHER_SET3",
    "selectedMarket": "Martlock",
    "otherMarket": "Black Market",
    "Buying_Price": 1447,
    "Selling_Price": 1647,
    "silver_profit": 200,
    "Ratio": 0.12143290831815422
  },
  {
    "itemId": "T6_BAG_INSIGHT@1",
    "itemName": "Master's Satchel of Insight",
    "itemTag": "@ITEMS_T6_BAG_INSIGHT",
    "selectedMarket": "Martlock",
    "otherMarket": "Black Market",
    "Buying_Price": 76994,
    "Selling_Price": 87600,
    "silver_profit": 10606,
    "Ratio": 0.1210730593607306
  },
  {
    "itemId": "T7_2H_KNUCKLES_SET3",
    "itemName": "Grandmaster's Spiked Gauntlets",
    "itemTag": "@ITEMS_T7_2H_KNUCKLES_SET3",
    "selectedMarket": "Martlock",
    "otherMarket": "Black Market",
    "Buying_Price": 189948,
    "Selling_Price": 216080,
    "silver_profit": 26132,
    "Ratio": 0.1209366901147723
  },
  {
    "itemId": "T5_BAG",
    "itemName": "Expert's Bag",
    "itemTag": "@ITEMS_T5_BAG",
    "selectedMarket": "Martlock",
    "otherMarket": "Black Market",
    "Buying_Price": 11662,
    "Selling_Price": 13140,
    "silver_profit": 1478,
    "Ratio": 0.11248097412480974
  },
  {
    "itemId": "T4_BAG@1",
    "itemName": "Adept's Bag",
    "itemTag": "@ITEMS_T4_BAG",
    "selectedMarket": "Martlock",
    "otherMarket": "Black Market",
    "Buying_Price": 4540,
    "Selling_Price": 5110,
    "silver_profit": 570,
    "Ratio": 0.11154598825831702
  },
  {
    "itemId": "T6_CAPEITEM_FW_THETFORD",
    "itemName": "Master's Thetford Cape",
    "itemTag": "@ITEMS_T6_CAPEITEM_FW_THETFORD",
    "selectedMarket": "Martlock",
    "otherMarket": "Black Market",
    "Buying_Price": 210411,
    "Selling_Price": 236664,
    "silver_profit": 26253,
    "Ratio": 0.11092941892303011
  },
  {
    "itemId": "T6_HEAD_CLOTH_SET1",
    "itemName": "Master's Scholar Cowl",
    "itemTag": "@ITEMS_T6_HEAD_CLOTH_SET1",
    "selectedMarket": "Martlock",
    "otherMarket": "Black Market",
    "Buying_Price": 10393,
    "Selling_Price": 11680,
    "silver_profit": 1287,
    "Ratio": 0.11018835616438356
  },
  {
    "itemId": "T6_SHOES_CLOTH_KEEPER",
    "itemName": "Master's Druid Sandals",
    "itemTag": "@ITEMS_T6_SHOES_CLOTH_KEEPER",
    "selectedMarket": "Martlock",
    "otherMarket": "Black Market",
    "Buying_Price": 17900,
    "Selling_Price": 20064,
    "silver_profit": 2164,
    "Ratio": 0.1078548644338118
  },
  {
    "itemId": "T7_MAIN_HAMMER",
    "itemName": "Grandmaster's Hammer",
    "itemTag": "@ITEMS_T7_MAIN_HAMMER",
    "selectedMarket": "Martlock",
    "otherMarket": "Black Market",
    "Buying_Price": 60978,
    "Selling_Price": 67890,
    "silver_profit": 6912,
    "Ratio": 0.10181175430844012
  },
  {
    "itemId": "T5_HEAD_PLATE_AVALON",
    "itemName": "Expert's Helmet of Valor",
    "itemTag": "@ITEMS_T5_HEAD_PLATE_AVALON",
    "selectedMarket": "Martlock",
    "otherMarket": "Black Market",
    "Buying_Price": 21245,
    "Selling_Price": 23409,
    "silver_profit": 2164,
    "Ratio": 0.09244307744884446
  },
  {
    "itemId": "T7_SHOES_CLOTH_SET3",
    "itemName": "Grandmaster's Mage Sandals",
    "itemTag": "@ITEMS_T7_SHOES_CLOTH_SET3",
    "selectedMarket": "Martlock",
    "otherMarket": "Black Market",
    "Buying_Price": 27834,
    "Selling_Price": 30660,
    "silver_profit": 2826,
    "Ratio": 0.09217221135029355
  },
  {
    "itemId": "T5_2H_INFERNOSTAFF",
    "itemName": "Expert's Infernal Staff",
    "itemTag": "@ITEMS_T5_2H_INFERNOSTAFF",
    "selectedMarket": "Martlock",
    "otherMarket": "Black Market",
    "Buying_Price": 9977,
    "Selling_Price": 10950,
    "silver_profit": 973,
    "Ratio": 0.08885844748858447
  },
  {
    "itemId": "T5_HEAD_PLATE_SET2@1",
    "itemName": "Expert's Knight Helmet",
    "itemTag": "@ITEMS_T5_HEAD_PLATE_SET2",
    "selectedMarket": "Martlock",
    "otherMarket": "Black Market",
    "Buying_Price": 6999,
    "Selling_Price": 7665,
    "silver_profit": 666,
    "Ratio": 0.08688845401174168
  },
  {
    "itemId": "T4_ARMOR_LEATHER_ROYAL",
    "itemName": "Adept's Royal Jacket",
    "itemTag": "@ITEMS_T4_ARMOR_LEATHER_ROYAL",
    "selectedMarket": "Martlock",
    "otherMarket": "Black Market",
    "Buying_Price": 29979,
    "Selling_Price": 32376,
    "silver_profit": 2397,
    "Ratio": 0.07403632320237213
  },
  {
    "itemId": "T6_BAG",
    "itemName": "Master's Bag",
    "itemTag": "@ITEMS_T6_BAG",
    "selectedMarket": "Martlock",
    "otherMarket": "Black Market",
    "Buying_Price": 37980,
    "Selling_Price": 40880,
    "silver_profit": 2900,
    "Ratio": 0.07093933463796477
  },
  {
    "itemId": "T7_MAIN_CURSEDSTAFF",
    "itemName": "Grandmaster's Cursed Staff",
    "itemTag": "@ITEMS_T7_MAIN_CURSEDSTAFF",
    "selectedMarket": "Martlock",
    "otherMarket": "Black Market",
    "Buying_Price": 89982,
    "Selling_Price": 96360,
    "silver_profit": 6378,
    "Ratio": 0.0661892901618929
  },
  {
    "itemId": "T6_CAPEITEM_UNDEAD",
    "itemName": "Master's Undead Cape",
    "itemTag": "@ITEMS_T6_CAPEITEM_UNDEAD",
    "selectedMarket": "Martlock",
    "otherMarket": "Black Market",
    "Buying_Price": 318086,
    "Selling_Price": 340176,
    "silver_profit": 22090,
    "Ratio": 0.06493697380179672
  },
  {
    "itemId": "T5_HEAD_CLOTH_SET3@2",
    "itemName": "Expert's Mage Cowl",
    "itemTag": "@ITEMS_T5_HEAD_CLOTH_SET3",
    "selectedMarket": "Martlock",
    "otherMarket": "Black Market",
    "Buying_Price": 19976,
    "Selling_Price": 21170,
    "silver_profit": 1194,
    "Ratio": 0.05640056683986774
  },
  {
    "itemId": "T7_BAG_INSIGHT@1",
    "itemName": "Grandmaster's Satchel of Insight",
    "itemTag": "@ITEMS_T7_BAG_INSIGHT",
    "selectedMarket": "Martlock",
    "otherMarket": "Black Market",
    "Buying_Price": 220056,
    "Selling_Price": 230680,
    "silver_profit": 10624,
    "Ratio": 0.04605514132131091
  },
  {
    "itemId": "T4_2H_LONGBOW@1",
    "itemName": "Adept's Longbow",
    "itemTag": "@ITEMS_T4_2H_LONGBOW",
    "selectedMarket": "Martlock",
    "otherMarket": "Black Market",
    "Buying_Price": 2094,
    "Selling_Price": 2190,
    "silver_profit": 96,
    "Ratio": 0.043835616438356165
  },
  {
    "itemId": "T5_2H_TOOL_HAMMER",
    "itemName": "Expert's Stone Hammer",
    "itemTag": "@ITEMS_T5_2H_TOOL_HAMMER",
    "selectedMarket": "Martlock",
    "otherMarket": "Black Market",
    "Buying_Price": 4218,
    "Selling_Price": 4392,
    "silver_profit": 174,
    "Ratio": 0.03961748633879782
  },
  {
    "itemId": "T7_ARMOR_CLOTH_SET1",
    "itemName": "Grandmaster's Scholar Robe",
    "itemTag": "@ITEMS_T7_ARMOR_CLOTH_SET1",
    "selectedMarket": "Martlock",
    "otherMarket": "Black Market",
    "Buying_Price": 56984,
    "Selling_Price": 58400,
    "silver_profit": 1416,
    "Ratio": 0.024246575342465753
  },
  {
    "itemId": "T4_SHOES_CLOTH_ROYAL@1",
    "itemName": "Adept's Royal Sandals",
    "itemTag": "@ITEMS_T4_SHOES_CLOTH_ROYAL",
    "selectedMarket": "Martlock",
    "otherMarket": "Black Market",
    "Buying_Price": 20466,
    "Selling_Price": 20705,
    "silver_profit": 239,
    "Ratio": 0.011543105530065201
  },
  {
    "itemId": "T6_ARMOR_LEATHER_SET1@1",
    "itemName": "Master's Mercenary Jacket",
    "itemTag": "@ITEMS_T6_ARMOR_LEATHER_SET1",
    "selectedMarket": "Martlock",
    "otherMarket": "Black Market",
    "Buying_Price": 69499,
    "Selling_Price": 70080,
    "silver_profit": 581,
    "Ratio": 0.008290525114155251
  },
  {
    "itemId": "T6_CAPE",
    "itemName": "Master's Cape",
    "itemTag": "@ITEMS_T6_CAPE",
    "selectedMarket": "Martlock",
    "otherMarket": "Black Market",
    "Buying_Price": 16368,
    "Selling_Price": 16425,
    "silver_profit": 57,
    "Ratio": 0.003470319634703196
  },
  {
    "itemId": "T6_ARMOR_LEATHER_SET1",
    "itemName": "Master's Mercenary Jacket",
    "itemTag": "@ITEMS_T6_ARMOR_LEATHER_SET1",
    "selectedMarket": "Martlock",
    "otherMarket": "Black Market",
    "Buying_Price": 30492,
    "Selling_Price": 30528,
    "silver_profit": 36,
    "Ratio": 0.0011792452830188679
  },
  {
    "itemId": "T6_HEAD_CLOTH_SET3",
    "itemName": "Master's Mage Cowl",
    "itemTag": "@ITEMS_T6_HEAD_CLOTH_SET3",
    "selectedMarket": "Martlock",
    "otherMarket": "Black Market",
    "Buying_Price": 8393,
    "Selling_Price": 8395,
    "silver_profit": 2,
    "Ratio": 0.00023823704586063132
  },
  {
    "itemId": "T5_OFF_TORCH",
    "itemName": "Expert's Torch",
    "itemTag": "@ITEMS_T5_OFF_TORCH",
    "selectedMarket": "Martlock",
    "otherMarket": "Black Market",
    "Buying_Price": 2379,
    "Selling_Price": 2379,
    "silver_profit": 0,
    "Ratio": 0
  },
  {
    "itemId": "T5_HEAD_CLOTH_HELL@1",
    "itemName": "Expert's Fiend Cowl",
    "itemTag": "@ITEMS_T5_HEAD_CLOTH_HELL",
    "selectedMarket": "Martlock",
    "otherMarket": "Black Market",
    "Buying_Price": 109996,
    "Selling_Price": 109436,
    "silver_profit": -560,
    "Ratio": -0.005117146094520998
  },
  {
    "itemId": "T5_ARMOR_CLOTH_SET2@1",
    "itemName": "Expert's Cleric Robe",
    "itemTag": "@ITEMS_T5_ARMOR_CLOTH_SET2",
    "selectedMarket": "Martlock",
    "otherMarket": "Black Market",
    "Buying_Price": 13999,
    "Selling_Price": 13870,
    "silver_profit": -129,
    "Ratio": -0.009300648882480172
  },
  {
    "itemId": "T5_CAPEITEM_UNDEAD@3",
    "itemName": "Expert's Undead Cape",
    "itemTag": "@ITEMS_T5_CAPEITEM_UNDEAD",
    "selectedMarket": "Martlock",
    "otherMarket": "Black Market",
    "Buying_Price": 384817,
    "Selling_Price": 379512,
    "silver_profit": -5305,
    "Ratio": -0.01397847762389595
  },
  {
    "itemId": "T8_BAG",
    "itemName": "Elder's Bag",
    "itemTag": "@ITEMS_T8_BAG",
    "selectedMarket": "Martlock",
    "otherMarket": "Black Market",
    "Buying_Price": 228459,
    "Selling_Price": 224840,
    "silver_profit": -3619,
    "Ratio": -0.016095890410958904
  },
  {
    "itemId": "T7_BAG_INSIGHT",
    "itemName": "Grandmaster's Satchel of Insight",
    "itemTag": "@ITEMS_T7_BAG_INSIGHT",
    "selectedMarket": "Martlock",
    "otherMarket": "Black Market",
    "Buying_Price": 125050,
    "Selling_Price": 121180,
    "silver_profit": -3870,
    "Ratio": -0.031935963030203005
  },
  {
    "itemId": "T8_2H_TOOL_HAMMER",
    "itemName": "Elder's Stone Hammer",
    "itemTag": "@ITEMS_T8_2H_TOOL_HAMMER",
    "selectedMarket": "Martlock",
    "otherMarket": "Black Market",
    "Buying_Price": 96896,
    "Selling_Price": 93440,
    "silver_profit": -3456,
    "Ratio": -0.036986301369863014
  },
  {
    "itemId": "T4_HEAD_CLOTH_ROYAL",
    "itemName": "Adept's Royal Cowl",
    "itemTag": "@ITEMS_T4_HEAD_CLOTH_ROYAL",
    "selectedMarket": "Martlock",
    "otherMarket": "Black Market",
    "Buying_Price": 20003,
    "Selling_Price": 19038,
    "silver_profit": -965,
    "Ratio": -0.05068809748923206
  },
  {
    "itemId": "T5_2H_CLAYMORE@1",
    "itemName": "Expert's Claymore",
    "itemTag": "@ITEMS_T5_2H_CLAYMORE",
    "selectedMarket": "Martlock",
    "otherMarket": "Black Market",
    "Buying_Price": 19999,
    "Selling_Price": 18980,
    "silver_profit": -1019,
    "Ratio": -0.05368809272918862
  },
  {
    "itemId": "T3_MOUNT_HORSE",
    "itemName": "Journeyman's Riding Horse",
    "itemTag": "@ITEMS_T3_MOUNT_HORSE",
    "selectedMarket": "Martlock",
    "otherMarket": "Black Market",
    "Buying_Price": 11429,
    "Selling_Price": 10841,
    "silver_profit": -588,
    "Ratio": -0.05423853888017711
  },
  {
    "itemId": "T5_2H_DUALSWORD",
    "itemName": "Expert's Dual Swords",
    "itemTag": "@ITEMS_T5_2H_DUALSWORD",
    "selectedMarket": "Martlock",
    "otherMarket": "Black Market",
    "Buying_Price": 8500,
    "Selling_Price": 8030,
    "silver_profit": -470,
    "Ratio": -0.058530510585305104
  },
  {
    "itemId": "T6_MAIN_DAGGER",
    "itemName": "Master's Dagger",
    "itemTag": "@ITEMS_T6_MAIN_DAGGER",
    "selectedMarket": "Martlock",
    "otherMarket": "Black Market",
    "Buying_Price": 40988,
    "Selling_Price": 37230,
    "silver_profit": -3758,
    "Ratio": -0.10094010206822455
  },
  {
    "itemId": "T4_CAPEITEM_FW_LYMHURST",
    "itemName": "Adept's Lymhurst Cape",
    "itemTag": "@ITEMS_T4_CAPEITEM_FW_LYMHURST",
    "selectedMarket": "Martlock",
    "otherMarket": "Black Market",
    "Buying_Price": 67731,
    "Selling_Price": 61104,
    "silver_profit": -6627,
    "Ratio": -0.10845443833464258
  },
  {
    "itemId": "T3_2H_TOOL_KNIFE",
    "itemName": "Journeyman's Skinning Knife",
    "itemTag": "@ITEMS_T3_2H_TOOL_KNIFE",
    "selectedMarket": "Martlock",
    "otherMarket": "Black Market",
    "Buying_Price": 616,
    "Selling_Price": 552,
    "silver_profit": -64,
    "Ratio": -0.11594202898550725
  },
  {
    "itemId": "T3_MAIN_DAGGER",
    "itemName": "Journeyman's Dagger",
    "itemTag": "@ITEMS_T3_MAIN_DAGGER",
    "selectedMarket": "Martlock",
    "otherMarket": "Black Market",
    "Buying_Price": 1234,
    "Selling_Price": 1096,
    "silver_profit": -138,
    "Ratio": -0.1259124087591241
  },
  {
    "itemId": "T4_2H_DOUBLEBLADEDSTAFF",
    "itemName": "Adept's Double Bladed Staff",
    "itemTag": "@ITEMS_T4_2H_DOUBLEBLADEDSTAFF",
    "selectedMarket": "Martlock",
    "otherMarket": "Black Market",
    "Buying_Price": 3297,
    "Selling_Price": 2920,
    "silver_profit": -377,
    "Ratio": -0.1291095890410959
  },
  {
    "itemId": "T5_2H_HALBERD",
    "itemName": "Expert's Halberd",
    "itemTag": "@ITEMS_T5_2H_HALBERD",
    "selectedMarket": "Martlock",
    "otherMarket": "Black Market",
    "Buying_Price": 13890,
    "Selling_Price": 12222,
    "silver_profit": -1668,
    "Ratio": -0.13647520864015708
  },
  {
    "itemId": "T4_CAPEITEM_FW_FORTSTERLING@1",
    "itemName": "Adept's Fort Sterling Cape",
    "itemTag": "@ITEMS_T4_CAPEITEM_FW_FORTSTERLING",
    "selectedMarket": "Martlock",
    "otherMarket": "Black Market",
    "Buying_Price": 71998,
    "Selling_Price": 60065,
    "silver_profit": -11933,
    "Ratio": -0.1986681095479897
  },
  {
    "itemId": "T8_CAPE",
    "itemName": "Elder's Cape",
    "itemTag": "@ITEMS_T8_CAPE",
    "selectedMarket": "Martlock",
    "otherMarket": "Black Market",
    "Buying_Price": 96990,
    "Selling_Price": 80300,
    "silver_profit": -16690,
    "Ratio": -0.2078455790784558
  },
  {
    "itemId": "T5_SHOES_LEATHER_SET2@1",
    "itemName": "Expert's Hunter Shoes",
    "itemTag": "@ITEMS_T5_SHOES_LEATHER_SET2",
    "selectedMarket": "Martlock",
    "otherMarket": "Black Market",
    "Buying_Price": 3999,
    "Selling_Price": 3285,
    "silver_profit": -714,
    "Ratio": -0.217351598173516
  },
  {
    "itemId": "T4_CAPEITEM_FW_MARTLOCK@1",
    "itemName": "Adept's Martlock Cape",
    "itemTag": "@ITEMS_T4_CAPEITEM_FW_MARTLOCK",
    "selectedMarket": "Martlock",
    "otherMarket": "Black Market",
    "Buying_Price": 68999,
    "Selling_Price": 55827,
    "silver_profit": -13172,
    "Ratio": -0.2359431816146309
  },
  {
    "itemId": "T4_CAPEITEM_FW_MARTLOCK",
    "itemName": "Adept's Martlock Cape",
    "itemTag": "@ITEMS_T4_CAPEITEM_FW_MARTLOCK",
    "selectedMarket": "Martlock",
    "otherMarket": "Black Market",
    "Buying_Price": 64990,
    "Selling_Price": 52326,
    "silver_profit": -12664,
    "Ratio": -0.24202117494171158
  },
  {
    "itemId": "T6_SHOES_PLATE_SET3",
    "itemName": "Master's Guardian Boots",
    "itemTag": "@ITEMS_T6_SHOES_PLATE_SET3",
    "selectedMarket": "Martlock",
    "otherMarket": "Black Market",
    "Buying_Price": 8168,
    "Selling_Price": 6570,
    "silver_profit": -1598,
    "Ratio": -0.2432267884322679
  },
  {
    "itemId": "T7_HEAD_LEATHER_SET1@1",
    "itemName": "Grandmaster's Mercenary Hood",
    "itemTag": "@ITEMS_T7_HEAD_LEATHER_SET1",
    "selectedMarket": "Martlock",
    "otherMarket": "Black Market",
    "Buying_Price": 67993,
    "Selling_Price": 54020,
    "silver_profit": -13973,
    "Ratio": -0.25866345797852647
  },
  {
    "itemId": "T4_CAPEITEM_UNDEAD",
    "itemName": "Adept's Undead Cape",
    "itemTag": "@ITEMS_T4_CAPEITEM_UNDEAD",
    "selectedMarket": "Martlock",
    "otherMarket": "Black Market",
    "Buying_Price": 289984,
    "Selling_Price": 228000,
    "silver_profit": -61984,
    "Ratio": -0.271859649122807
  },
  {
    "itemId": "T5_OFF_BOOK",
    "itemName": "Expert's Tome of Spells",
    "itemTag": "@ITEMS_T5_OFF_BOOK",
    "selectedMarket": "Martlock",
    "otherMarket": "Black Market",
    "Buying_Price": 3290,
    "Selling_Price": 2562,
    "silver_profit": -728,
    "Ratio": -0.28415300546448086
  },
  {
    "itemId": "T7_HEAD_CLOTH_SET2",
    "itemName": "Grandmaster's Cleric Cowl",
    "itemTag": "@ITEMS_T7_HEAD_CLOTH_SET2",
    "selectedMarket": "Martlock",
    "otherMarket": "Black Market",
    "Buying_Price": 32078,
    "Selling_Price": 24820,
    "silver_profit": -7258,
    "Ratio": -0.2924254633360193
  },
  {
    "itemId": "T4_CAPEITEM_FW_MARTLOCK@2",
    "itemName": "Adept's Martlock Cape",
    "itemTag": "@ITEMS_T4_CAPEITEM_FW_MARTLOCK",
    "selectedMarket": "Martlock",
    "otherMarket": "Black Market",
    "Buying_Price": 79991,
    "Selling_Price": 60528,
    "silver_profit": -19463,
    "Ratio": -0.3215536611155168
  },
  {
    "itemId": "T5_ARMOR_LEATHER_SET2@1",
    "itemName": "Expert's Hunter Jacket",
    "itemTag": "@ITEMS_T5_ARMOR_LEATHER_SET2",
    "selectedMarket": "Martlock",
    "otherMarket": "Black Market",
    "Buying_Price": 11945,
    "Selling_Price": 8760,
    "silver_profit": -3185,
    "Ratio": -0.3635844748858447
  },
  {
    "itemId": "T6_CAPEITEM_FW_BRIDGEWATCH@1",
    "itemName": "Master's Bridgewatch Cape",
    "itemTag": "@ITEMS_T6_CAPEITEM_FW_BRIDGEWATCH",
    "selectedMarket": "Martlock",
    "otherMarket": "Black Market",
    "Buying_Price": 211993,
    "Selling_Price": 155169,
    "silver_profit": -56824,
    "Ratio": -0.36620716766879985
  },
  {
    "itemId": "T4_CAPEITEM_FW_THETFORD@2",
    "itemName": "Adept's Thetford Cape",
    "itemTag": "@ITEMS_T4_CAPEITEM_FW_THETFORD",
    "selectedMarket": "Martlock",
    "otherMarket": "Black Market",
    "Buying_Price": 82000,
    "Selling_Price": 58588,
    "silver_profit": -23412,
    "Ratio": -0.3996040144739537
  },
  {
    "itemId": "T4_ARMOR_LEATHER_HELL",
    "itemName": "Adept's Hellion Jacket",
    "itemTag": "@ITEMS_T4_ARMOR_LEATHER_HELL",
    "selectedMarket": "Martlock",
    "otherMarket": "Black Market",
    "Buying_Price": 73909,
    "Selling_Price": 52635,
    "silver_profit": -21274,
    "Ratio": -0.40417972831765936
  },
  {
    "itemId": "T6_BAG@1",
    "itemName": "Master's Bag",
    "itemTag": "@ITEMS_T6_BAG",
    "selectedMarket": "Martlock",
    "otherMarket": "Black Market",
    "Buying_Price": 60984,
    "Selling_Price": 42340,
    "silver_profit": -18644,
    "Ratio": -0.44034010392064243
  },
  {
    "itemId": "T6_ARMOR_PLATE_SET3@1",
    "itemName": "Master's Guardian Armor",
    "itemTag": "@ITEMS_T6_ARMOR_PLATE_SET3",
    "selectedMarket": "Martlock",
    "otherMarket": "Black Market",
    "Buying_Price": 39987,
    "Selling_Price": 27740,
    "silver_profit": -12247,
    "Ratio": -0.441492429704398
  },
  {
    "itemId": "T4_CAPEITEM_FW_MARTLOCK@3",
    "itemName": "Adept's Martlock Cape",
    "itemTag": "@ITEMS_T4_CAPEITEM_FW_MARTLOCK",
    "selectedMarket": "Martlock",
    "otherMarket": "Black Market",
    "Buying_Price": 114208,
    "Selling_Price": 78312,
    "silver_profit": -35896,
    "Ratio": -0.4583716416385739
  },
  {
    "itemId": "T5_2H_TOOL_PICK",
    "itemName": "Expert's Pickaxe",
    "itemTag": "@ITEMS_T5_2H_TOOL_PICK",
    "selectedMarket": "Martlock",
    "otherMarket": "Black Market",
    "Buying_Price": 4052,
    "Selling_Price": 2745,
    "silver_profit": -1307,
    "Ratio": -0.4761384335154827
  },
  {
    "itemId": "T5_MAIN_SPEAR",
    "itemName": "Expert's Spear",
    "itemTag": "@ITEMS_T5_MAIN_SPEAR",
    "selectedMarket": "Martlock",
    "otherMarket": "Black Market",
    "Buying_Price": 6516,
    "Selling_Price": 4384,
    "silver_profit": -2132,
    "Ratio": -0.4863138686131387
  },
  {
    "itemId": "T6_OFF_TORCH",
    "itemName": "Master's Torch",
    "itemTag": "@ITEMS_T6_OFF_TORCH",
    "selectedMarket": "Martlock",
    "otherMarket": "Black Market",
    "Buying_Price": 7775,
    "Selling_Price": 5110,
    "silver_profit": -2665,
    "Ratio": -0.5215264187866928
  },
  {
    "itemId": "T5_ARMOR_LEATHER_SET1@3",
    "itemName": "Expert's Mercenary Jacket",
    "itemTag": "@ITEMS_T5_ARMOR_LEATHER_SET1",
    "selectedMarket": "Martlock",
    "otherMarket": "Black Market",
    "Buying_Price": 195909,
    "Selling_Price": 125560,
    "silver_profit": -70349,
    "Ratio": -0.5602819369225868
  },
  {
    "itemId": "T4_ARMOR_LEATHER_SET1@2",
    "itemName": "Adept's Mercenary Jacket",
    "itemTag": "@ITEMS_T4_ARMOR_LEATHER_SET1",
    "selectedMarket": "Martlock",
    "otherMarket": "Black Market",
    "Buying_Price": 29999,
    "Selling_Price": 18980,
    "silver_profit": -11019,
    "Ratio": -0.5805584826132771
  },
  {
    "itemId": "T4_ARMOR_LEATHER_SET1@1",
    "itemName": "Adept's Mercenary Jacket",
    "itemTag": "@ITEMS_T4_ARMOR_LEATHER_SET1",
    "selectedMarket": "Martlock",
    "otherMarket": "Black Market",
    "Buying_Price": 2898,
    "Selling_Price": 1825,
    "silver_profit": -1073,
    "Ratio": -0.5879452054794521
  },
  {
    "itemId": "T4_ARMOR_LEATHER_SET3",
    "itemName": "Adept's Assassin Jacket",
    "itemTag": "@ITEMS_T4_ARMOR_LEATHER_SET3",
    "selectedMarket": "Martlock",
    "otherMarket": "Black Market",
    "Buying_Price": 900,
    "Selling_Price": 549,
    "silver_profit": -351,
    "Ratio": -0.639344262295082
  },
  {
    "itemId": "T6_ARMOR_PLATE_SET2@1",
    "itemName": "Master's Knight Armor",
    "itemTag": "@ITEMS_T6_ARMOR_PLATE_SET2",
    "selectedMarket": "Martlock",
    "otherMarket": "Black Market",
    "Buying_Price": 43999,
    "Selling_Price": 26280,
    "silver_profit": -17719,
    "Ratio": -0.6742389649923897
  },
  {
    "itemId": "T4_HEAD_PLATE_AVALON",
    "itemName": "Adept's Helmet of Valor",
    "itemTag": "@ITEMS_T4_HEAD_PLATE_AVALON",
    "selectedMarket": "Martlock",
    "otherMarket": "Black Market",
    "Buying_Price": 23998,
    "Selling_Price": 14322,
    "silver_profit": -9676,
    "Ratio": -0.6756039659265466
  },
  {
    "itemId": "T8_HEAD_LEATHER_SET1",
    "itemName": "Elder's Mercenary Hood",
    "itemTag": "@ITEMS_T8_HEAD_LEATHER_SET1",
    "selectedMarket": "Martlock",
    "otherMarket": "Black Market",
    "Buying_Price": 98000,
    "Selling_Price": 58400,
    "silver_profit": -39600,
    "Ratio": -0.678082191780822
  },
  {
    "itemId": "T6_SHOES_LEATHER_SET1",
    "itemName": "Master's Mercenary Shoes",
    "itemTag": "@ITEMS_T6_SHOES_LEATHER_SET1",
    "selectedMarket": "Martlock",
    "otherMarket": "Black Market",
    "Buying_Price": 12937,
    "Selling_Price": 7665,
    "silver_profit": -5272,
    "Ratio": -0.6878016960208742
  },
  {
    "itemId": "T3_ARMOR_PLATE_SET1",
    "itemName": "Journeyman's Soldier Armor",
    "itemTag": "@ITEMS_T3_ARMOR_PLATE_SET1",
    "selectedMarket": "Martlock",
    "otherMarket": "Black Market",
    "Buying_Price": 309,
    "Selling_Price": 182,
    "silver_profit": -127,
    "Ratio": -0.6978021978021978
  },
  {
    "itemId": "T4_ARMOR_PLATE_KEEPER",
    "itemName": "Adept's Judicator Armor",
    "itemTag": "@ITEMS_T4_ARMOR_PLATE_KEEPER",
    "selectedMarket": "Martlock",
    "otherMarket": "Black Market",
    "Buying_Price": 30995,
    "Selling_Price": 18072,
    "silver_profit": -12923,
    "Ratio": -0.7150841080123949
  },
  {
    "itemId": "T7_HEAD_LEATHER_SET3@1",
    "itemName": "Grandmaster's Assassin Hood",
    "itemTag": "@ITEMS_T7_HEAD_LEATHER_SET3",
    "selectedMarket": "Martlock",
    "otherMarket": "Black Market",
    "Buying_Price": 133863,
    "Selling_Price": 75920,
    "silver_profit": -57943,
    "Ratio": -0.7632112750263436
  },
  {
    "itemId": "T4_CAPEITEM_FW_THETFORD",
    "itemName": "Adept's Thetford Cape",
    "itemTag": "@ITEMS_T4_CAPEITEM_FW_THETFORD",
    "selectedMarket": "Martlock",
    "otherMarket": "Black Market",
    "Buying_Price": 99998,
    "Selling_Price": 56658,
    "silver_profit": -43340,
    "Ratio": -0.7649405203148717
  },
  {
    "itemId": "T5_CAPE",
    "itemName": "Expert's Cape",
    "itemTag": "@ITEMS_T5_CAPE",
    "selectedMarket": "Martlock",
    "otherMarket": "Black Market",
    "Buying_Price": 7892,
    "Selling_Price": 4392,
    "silver_profit": -3500,
    "Ratio": -0.7969034608378871
  },
  {
    "itemId": "T5_ARMOR_CLOTH_SET3",
    "itemName": "Expert's Mage Robe",
    "itemTag": "@ITEMS_T5_ARMOR_CLOTH_SET3",
    "selectedMarket": "Martlock",
    "otherMarket": "Black Market",
    "Buying_Price": 4683,
    "Selling_Price": 2555,
    "silver_profit": -2128,
    "Ratio": -0.8328767123287671
  },
  {
    "itemId": "T4_CAPEITEM_FW_BRIDGEWATCH@1",
    "itemName": "Adept's Bridgewatch Cape",
    "itemTag": "@ITEMS_T4_CAPEITEM_FW_BRIDGEWATCH",
    "selectedMarket": "Martlock",
    "otherMarket": "Black Market",
    "Buying_Price": 58450,
    "Selling_Price": 30750,
    "silver_profit": -27700,
    "Ratio": -0.9008130081300812
  },
  {
    "itemId": "T3_2H_TOOL_SICKLE",
    "itemName": "Journeyman's Sickle",
    "itemTag": "@ITEMS_T3_2H_TOOL_SICKLE",
    "selectedMarket": "Martlock",
    "otherMarket": "Black Market",
    "Buying_Price": 266,
    "Selling_Price": 138,
    "silver_profit": -128,
    "Ratio": -0.927536231884058
  },
  {
    "itemId": "T6_ARMOR_CLOTH_SET2@2",
    "itemName": "Master's Cleric Robe",
    "itemTag": "@ITEMS_T6_ARMOR_CLOTH_SET2",
    "selectedMarket": "Martlock",
    "otherMarket": "Black Market",
    "Buying_Price": 150547,
    "Selling_Price": 75920,
    "silver_profit": -74627,
    "Ratio": -0.9829689146469969
  },
  {
    "itemId": "T4_SHOES_PLATE_SET2",
    "itemName": "Adept's Knight Boots",
    "itemTag": "@ITEMS_T4_SHOES_PLATE_SET2",
    "selectedMarket": "Martlock",
    "otherMarket": "Black Market",
    "Buying_Price": 549,
    "Selling_Price": 273,
    "silver_profit": -276,
    "Ratio": -1.010989010989011
  },
  {
    "itemId": "T6_SHOES_PLATE_AVALON@2",
    "itemName": "Master's Boots of Valor",
    "itemTag": "@ITEMS_T6_SHOES_PLATE_AVALON",
    "selectedMarket": "Martlock",
    "otherMarket": "Black Market",
    "Buying_Price": 319918,
    "Selling_Price": 158424,
    "silver_profit": -161494,
    "Ratio": -1.0193783770135838
  },
  {
    "itemId": "T6_SHOES_CLOTH_SET3",
    "itemName": "Master's Mage Sandals",
    "itemTag": "@ITEMS_T6_SHOES_CLOTH_SET3",
    "selectedMarket": "Martlock",
    "otherMarket": "Black Market",
    "Buying_Price": 8897,
    "Selling_Price": 4380,
    "silver_profit": -4517,
    "Ratio": -1.0312785388127854
  },
  {
    "itemId": "T6_HEAD_CLOTH_SET1@1",
    "itemName": "Master's Scholar Cowl",
    "itemTag": "@ITEMS_T6_HEAD_CLOTH_SET1",
    "selectedMarket": "Martlock",
    "otherMarket": "Black Market",
    "Buying_Price": 17992,
    "Selling_Price": 8760,
    "silver_profit": -9232,
    "Ratio": -1.0538812785388127
  },
  {
    "itemId": "T6_ARMOR_CLOTH_SET2@1",
    "itemName": "Master's Cleric Robe",
    "itemTag": "@ITEMS_T6_ARMOR_CLOTH_SET2",
    "selectedMarket": "Martlock",
    "otherMarket": "Black Market",
    "Buying_Price": 39000,
    "Selling_Price": 18980,
    "silver_profit": -20020,
    "Ratio": -1.0547945205479452
  },
  {
    "itemId": "T4_OFF_HORN_KEEPER",
    "itemName": "Adept's Mistcaller",
    "itemTag": "@ITEMS_T4_OFF_HORN_KEEPER",
    "selectedMarket": "Martlock",
    "otherMarket": "Black Market",
    "Buying_Price": 8000,
    "Selling_Price": 3876,
    "silver_profit": -4124,
    "Ratio": -1.0639834881320949
  },
  {
    "itemId": "T4_CAPEITEM_FW_CAERLEON",
    "itemName": "Adept's Caerleon Cape",
    "itemTag": "@ITEMS_T4_CAPEITEM_FW_CAERLEON",
    "selectedMarket": "Martlock",
    "otherMarket": "Black Market",
    "Buying_Price": 74984,
    "Selling_Price": 35796,
    "silver_profit": -39188,
    "Ratio": -1.0947591909710581
  },
  {
    "itemId": "T5_2H_GLACIALSTAFF",
    "itemName": "Expert's Glacial Staff",
    "itemTag": "@ITEMS_T5_2H_GLACIALSTAFF",
    "selectedMarket": "Martlock",
    "otherMarket": "Black Market",
    "Buying_Price": 10999,
    "Selling_Price": 5110,
    "silver_profit": -5889,
    "Ratio": -1.1524461839530333
  },
  {
    "itemId": "T4_ARMOR_LEATHER_HELL@3",
    "itemName": "Adept's Hellion Jacket",
    "itemTag": "@ITEMS_T4_ARMOR_LEATHER_HELL",
    "selectedMarket": "Martlock",
    "otherMarket": "Black Market",
    "Buying_Price": 154988,
    "Selling_Price": 70268,
    "silver_profit": -84720,
    "Ratio": -1.2056697216371606
  },
  {
    "itemId": "T6_SHOES_LEATHER_HELL",
    "itemName": "Master's Hellion Shoes",
    "itemTag": "@ITEMS_T6_SHOES_LEATHER_HELL",
    "selectedMarket": "Martlock",
    "otherMarket": "Black Market",
    "Buying_Price": 23998,
    "Selling_Price": 10863,
    "silver_profit": -13135,
    "Ratio": -1.2091503267973855
  },
  {
    "itemId": "T4_CAPEITEM_FW_THETFORD@1",
    "itemName": "Adept's Thetford Cape",
    "itemTag": "@ITEMS_T4_CAPEITEM_FW_THETFORD",
    "selectedMarket": "Martlock",
    "otherMarket": "Black Market",
    "Buying_Price": 136999,
    "Selling_Price": 57195,
    "silver_profit": -79804,
    "Ratio": -1.3952967916775942
  },
  {
    "itemId": "T5_SHOES_LEATHER_SET1",
    "itemName": "Expert's Mercenary Shoes",
    "itemTag": "@ITEMS_T5_SHOES_LEATHER_SET1",
    "selectedMarket": "Martlock",
    "otherMarket": "Black Market",
    "Buying_Price": 3072,
    "Selling_Price": 1281,
    "silver_profit": -1791,
    "Ratio": -1.3981264637002342
  },
  {
    "itemId": "T4_SHOES_PLATE_SET1",
    "itemName": "Adept's Soldier Boots",
    "itemTag": "@ITEMS_T4_SHOES_PLATE_SET1",
    "selectedMarket": "Martlock",
    "otherMarket": "Black Market",
    "Buying_Price": 657,
    "Selling_Price": 273,
    "silver_profit": -384,
    "Ratio": -1.4065934065934067
  },
  {
    "itemId": "T5_SHOES_PLATE_SET1@1",
    "itemName": "Expert's Soldier Boots",
    "itemTag": "@ITEMS_T5_SHOES_PLATE_SET1",
    "selectedMarket": "Martlock",
    "otherMarket": "Black Market",
    "Buying_Price": 7177,
    "Selling_Price": 2920,
    "silver_profit": -4257,
    "Ratio": -1.457876712328767
  },
  {
    "itemId": "T5_2H_ENIGMATICSTAFF",
    "itemName": "Expert's Enigmatic Staff",
    "itemTag": "@ITEMS_T5_2H_ENIGMATICSTAFF",
    "selectedMarket": "Martlock",
    "otherMarket": "Black Market",
    "Buying_Price": 8987,
    "Selling_Price": 3650,
    "silver_profit": -5337,
    "Ratio": -1.4621917808219178
  },
  {
    "itemId": "T5_MAIN_CURSEDSTAFF@1",
    "itemName": "Expert's Cursed Staff",
    "itemTag": "@ITEMS_T5_MAIN_CURSEDSTAFF",
    "selectedMarket": "Martlock",
    "otherMarket": "Black Market",
    "Buying_Price": 22111,
    "Selling_Price": 8760,
    "silver_profit": -13351,
    "Ratio": -1.5240867579908677
  },
  {
    "itemId": "T6_HEAD_LEATHER_SET2",
    "itemName": "Master's Hunter Hood",
    "itemTag": "@ITEMS_T6_HEAD_LEATHER_SET2",
    "selectedMarket": "Martlock",
    "otherMarket": "Black Market",
    "Buying_Price": 18886,
    "Selling_Price": 7300,
    "silver_profit": -11586,
    "Ratio": -1.587123287671233
  },
  {
    "itemId": "T4_MAIN_RAPIER_MORGANA",
    "itemName": "Adept's Bloodletter",
    "itemTag": "@ITEMS_T4_MAIN_RAPIER_MORGANA",
    "selectedMarket": "Martlock",
    "otherMarket": "Black Market",
    "Buying_Price": 15792,
    "Selling_Price": 6014,
    "silver_profit": -9778,
    "Ratio": -1.6258729630861324
  },
  {
    "itemId": "T4_SHOES_LEATHER_SET1@1",
    "itemName": "Adept's Mercenary Shoes",
    "itemTag": "@ITEMS_T4_SHOES_LEATHER_SET1",
    "selectedMarket": "Martlock",
    "otherMarket": "Black Market",
    "Buying_Price": 984,
    "Selling_Price": 366,
    "silver_profit": -618,
    "Ratio": -1.6885245901639345
  },
  {
    "itemId": "T6_2H_NATURESTAFF@1",
    "itemName": "Master's Great Nature Staff",
    "itemTag": "@ITEMS_T6_2H_NATURESTAFF",
    "selectedMarket": "Martlock",
    "otherMarket": "Black Market",
    "Buying_Price": 99995,
    "Selling_Price": 35040,
    "silver_profit": -64955,
    "Ratio": -1.853738584474886
  },
  {
    "itemId": "T4_2H_TOOL_HAMMER",
    "itemName": "Adept's Stone Hammer",
    "itemTag": "@ITEMS_T4_2H_TOOL_HAMMER",
    "selectedMarket": "Martlock",
    "otherMarket": "Black Market",
    "Buying_Price": 1327,
    "Selling_Price": 455,
    "silver_profit": -872,
    "Ratio": -1.9164835164835166
  },
  {
    "itemId": "T6_HEAD_PLATE_SET1",
    "itemName": "Master's Soldier Helmet",
    "itemTag": "@ITEMS_T6_HEAD_PLATE_SET1",
    "selectedMarket": "Martlock",
    "otherMarket": "Black Market",
    "Buying_Price": 8990,
    "Selling_Price": 2920,
    "silver_profit": -6070,
    "Ratio": -2.078767123287671
  },
  {
    "itemId": "T8_HEAD_PLATE_SET2",
    "itemName": "Elder's Knight Helmet",
    "itemTag": "@ITEMS_T8_HEAD_PLATE_SET2",
    "selectedMarket": "Martlock",
    "otherMarket": "Black Market",
    "Buying_Price": 86980,
    "Selling_Price": 27740,
    "silver_profit": -59240,
    "Ratio": -2.135544340302812
  },
  {
    "itemId": "T6_2H_TOOL_HAMMER",
    "itemName": "Master's Stone Hammer",
    "itemTag": "@ITEMS_T6_2H_TOOL_HAMMER",
    "selectedMarket": "Martlock",
    "otherMarket": "Black Market",
    "Buying_Price": 13995,
    "Selling_Price": 4380,
    "silver_profit": -9615,
    "Ratio": -2.1952054794520546
  },
  {
    "itemId": "T6_SHOES_PLATE_SET2",
    "itemName": "Master's Knight Boots",
    "itemTag": "@ITEMS_T6_SHOES_PLATE_SET2",
    "selectedMarket": "Martlock",
    "otherMarket": "Black Market",
    "Buying_Price": 8178,
    "Selling_Price": 2555,
    "silver_profit": -5623,
    "Ratio": -2.2007827788649705
  },
  {
    "itemId": "T6_2H_TOOL_SICKLE",
    "itemName": "Master's Sickle",
    "itemTag": "@ITEMS_T6_2H_TOOL_SICKLE",
    "selectedMarket": "Martlock",
    "otherMarket": "Black Market",
    "Buying_Price": 16991,
    "Selling_Price": 4745,
    "silver_profit": -12246,
    "Ratio": -2.580821917808219
  },
  {
    "itemId": "T4_ARMOR_LEATHER_SET2@1",
    "itemName": "Adept's Hunter Jacket",
    "itemTag": "@ITEMS_T4_ARMOR_LEATHER_SET2",
    "selectedMarket": "Martlock",
    "otherMarket": "Black Market",
    "Buying_Price": 2693,
    "Selling_Price": 730,
    "silver_profit": -1963,
    "Ratio": -2.6890410958904107
  },
  {
    "itemId": "T6_MAIN_CURSEDSTAFF@1",
    "itemName": "Master's Cursed Staff",
    "itemTag": "@ITEMS_T6_MAIN_CURSEDSTAFF",
    "selectedMarket": "Martlock",
    "otherMarket": "Black Market",
    "Buying_Price": 98999,
    "Selling_Price": 26280,
    "silver_profit": -72719,
    "Ratio": -2.7670852359208524
  },
  {
    "itemId": "T7_ARMOR_PLATE_SET1",
    "itemName": "Grandmaster's Soldier Armor",
    "itemTag": "@ITEMS_T7_ARMOR_PLATE_SET1",
    "selectedMarket": "Martlock",
    "otherMarket": "Black Market",
    "Buying_Price": 44370,
    "Selling_Price": 11680,
    "silver_profit": -32690,
    "Ratio": -2.7988013698630136
  },
  {
    "itemId": "T6_2H_AXE",
    "itemName": "Master's Greataxe",
    "itemTag": "@ITEMS_T6_2H_AXE",
    "selectedMarket": "Martlock",
    "otherMarket": "Black Market",
    "Buying_Price": 35355,
    "Selling_Price": 8760,
    "silver_profit": -26595,
    "Ratio": -3.035958904109589
  },
  {
    "itemId": "T5_HEAD_LEATHER_HELL",
    "itemName": "Expert's Hellion Hood",
    "itemTag": "@ITEMS_T5_HEAD_LEATHER_HELL",
    "selectedMarket": "Martlock",
    "otherMarket": "Black Market",
    "Buying_Price": 13000,
    "Selling_Price": 3190,
    "silver_profit": -9810,
    "Ratio": -3.0752351097178683
  },
  {
    "itemId": "T3_MAIN_AXE",
    "itemName": "Journeyman's Battleaxe",
    "itemTag": "@ITEMS_T3_MAIN_AXE",
    "selectedMarket": "Martlock",
    "otherMarket": "Black Market",
    "Buying_Price": 588,
    "Selling_Price": 137,
    "silver_profit": -451,
    "Ratio": -3.291970802919708
  },
  {
    "itemId": "T4_ARMOR_LEATHER_HELL@1",
    "itemName": "Adept's Hellion Jacket",
    "itemTag": "@ITEMS_T4_ARMOR_LEATHER_HELL",
    "selectedMarket": "Martlock",
    "otherMarket": "Black Market",
    "Buying_Price": 73710,
    "Selling_Price": 14558,
    "silver_profit": -59152,
    "Ratio": -4.063195493886523
  },
  {
    "itemId": "T4_CAPEITEM_FW_LYMHURST@3",
    "itemName": "Adept's Lymhurst Cape",
    "itemTag": "@ITEMS_T4_CAPEITEM_FW_LYMHURST",
    "selectedMarket": "Martlock",
    "otherMarket": "Black Market",
    "Buying_Price": 300006,
    "Selling_Price": 56475,
    "silver_profit": -243531,
    "Ratio": -4.312191235059761
  },
  {
    "itemId": "T4_HEAD_CLOTH_HELL@3",
    "itemName": "Adept's Fiend Cowl",
    "itemTag": "@ITEMS_T4_HEAD_CLOTH_HELL",
    "selectedMarket": "Martlock",
    "otherMarket": "Black Market",
    "Buying_Price": 114992,
    "Selling_Price": 21573,
    "silver_profit": -93419,
    "Ratio": -4.330366662031243
  },
  {
    "itemId": "T6_ARMOR_PLATE_SET3",
    "itemName": "Master's Guardian Armor",
    "itemTag": "@ITEMS_T6_ARMOR_PLATE_SET3",
    "selectedMarket": "Martlock",
    "otherMarket": "Black Market",
    "Buying_Price": 18869,
    "Selling_Price": 2920,
    "silver_profit": -15949,
    "Ratio": -5.461986301369863
  },
  {
    "itemId": "T7_HEAD_LEATHER_SET3",
    "itemName": "Grandmaster's Assassin Hood",
    "itemTag": "@ITEMS_T7_HEAD_LEATHER_SET3",
    "selectedMarket": "Martlock",
    "otherMarket": "Black Market",
    "Buying_Price": 54938,
    "Selling_Price": 8030,
    "silver_profit": -46908,
    "Ratio": -5.84159402241594
  },
  {
    "itemId": "T7_HEAD_PLATE_SET2",
    "itemName": "Grandmaster's Knight Helmet",
    "itemTag": "@ITEMS_T7_HEAD_PLATE_SET2",
    "selectedMarket": "Martlock",
    "otherMarket": "Black Market",
    "Buying_Price": 24386,
    "Selling_Price": 2920,
    "silver_profit": -21466,
    "Ratio": -7.351369863013699
  },
  {
    "itemId": "T5_CAPEITEM_FW_LYMHURST@3",
    "itemName": "Expert's Lymhurst Cape",
    "itemTag": "@ITEMS_T5_CAPEITEM_FW_LYMHURST",
    "selectedMarket": "Martlock",
    "otherMarket": "Black Market",
    "Buying_Price": 2000000,
    "Selling_Price": 216864,
    "silver_profit": -1783136,
    "Ratio": -8.222369780138704
  },
  {
    "itemId": "T6_2H_SPEAR",
    "itemName": "Master's Pike",
    "itemTag": "@ITEMS_T6_2H_SPEAR",
    "selectedMarket": "Martlock",
    "otherMarket": "Black Market",
    "Buying_Price": 27986,
    "Selling_Price": 2920,
    "silver_profit": -25066,
    "Ratio": -8.584246575342465
  },
  {
    "itemId": "T4_SHOES_CLOTH_ROYAL@3",
    "itemName": "Adept's Royal Sandals",
    "itemTag": "@ITEMS_T4_SHOES_CLOTH_ROYAL",
    "selectedMarket": "Martlock",
    "otherMarket": "Black Market",
    "Buying_Price": 64995,
    "Selling_Price": 6777,
    "silver_profit": -58218,
    "Ratio": -8.590526781761842
  },
  {
    "itemId": "T7_SHOES_LEATHER_SET3@1",
    "itemName": "Grandmaster's Assassin Shoes",
    "itemTag": "@ITEMS_T7_SHOES_LEATHER_SET3",
    "selectedMarket": "Martlock",
    "otherMarket": "Black Market",
    "Buying_Price": 79992,
    "Selling_Price": 7300,
    "silver_profit": -72692,
    "Ratio": -9.957808219178082
  },
  {
    "itemId": "T5_CAPEITEM_FW_CAERLEON@1",
    "itemName": "Expert's Caerleon Cape",
    "itemTag": "@ITEMS_T5_CAPEITEM_FW_CAERLEON",
    "selectedMarket": "Martlock",
    "otherMarket": "Black Market",
    "Buying_Price": 104939,
    "Selling_Price": 9042,
    "silver_profit": -95897,
    "Ratio": -10.605728821057289
  },
  {
    "itemId": "T6_2H_CURSEDSTAFF@1",
    "itemName": "Master's Great Cursed Staff",
    "itemTag": "@ITEMS_T6_2H_CURSEDSTAFF",
    "selectedMarket": "Martlock",
    "otherMarket": "Black Market",
    "Buying_Price": 69998,
    "Selling_Price": 5840,
    "silver_profit": -64158,
    "Ratio": -10.985958904109589
  },
  {
    "itemId": "T7_2H_ARCANESTAFF",
    "itemName": "Grandmaster's Great Arcane Staff",
    "itemTag": "@ITEMS_T7_2H_ARCANESTAFF",
    "selectedMarket": "Martlock",
    "otherMarket": "Black Market",
    "Buying_Price": 79999,
    "Selling_Price": 5840,
    "silver_profit": -74159,
    "Ratio": -12.69845890410959
  },
  {
    "itemId": "T5_2H_MACE",
    "itemName": "Expert's Heavy Mace",
    "itemTag": "@ITEMS_T5_2H_MACE",
    "selectedMarket": "Martlock",
    "otherMarket": "Black Market",
    "Buying_Price": 10954,
    "Selling_Price": 730,
    "silver_profit": -10224,
    "Ratio": -14.005479452054795
  },
  {
    "itemId": "T4_CAPEITEM_UNDEAD@1",
    "itemName": "Adept's Undead Cape",
    "itemTag": "@ITEMS_T4_CAPEITEM_UNDEAD",
    "selectedMarket": "Martlock",
    "otherMarket": "Black Market",
    "Buying_Price": 2449989,
    "Selling_Price": 136940,
    "silver_profit": -2313049,
    "Ratio": -16.890966846794218
  },
  {
    "itemId": "T6_MAIN_HOLYSTAFF",
    "itemName": "Master's Holy Staff",
    "itemTag": "@ITEMS_T6_MAIN_HOLYSTAFF",
    "selectedMarket": "Martlock",
    "otherMarket": "Black Market",
    "Buying_Price": 24469,
    "Selling_Price": 1095,
    "silver_profit": -23374,
    "Ratio": -21.34611872146119
  },
  {
    "itemId": "T4_SHOES_GATHERER_ORE",
    "itemName": "Adept's Miner Workboots",
    "itemTag": "@ITEMS_T4_SHOES_GATHERER_ORE",
    "selectedMarket": "Martlock",
    "otherMarket": "Black Market",
    "Buying_Price": 1796,
    "Selling_Price": 67,
    "silver_profit": -1729,
    "Ratio": -25.80597014925373
  },
  {
    "itemId": "T6_OFF_BOOK",
    "itemName": "Master's Tome of Spells",
    "itemTag": "@ITEMS_T6_OFF_BOOK",
    "selectedMarket": "Martlock",
    "otherMarket": "Black Market",
    "Buying_Price": 11543,
    "Selling_Price": 365,
    "silver_profit": -11178,
    "Ratio": -30.624657534246577
  },
  {
    "itemId": "T8_OFF_SHIELD",
    "itemName": "Elder's Shield",
    "itemTag": "@ITEMS_T8_OFF_SHIELD",
    "selectedMarket": "Martlock",
    "otherMarket": "Black Market",
    "Buying_Price": 865861,
    "Selling_Price": 26280,
    "silver_profit": -839581,
    "Ratio": -31.947526636225266
  },
  {
    "itemId": "T5_HEAD_LEATHER_SET3@3",
    "itemName": "Expert's Assassin Hood",
    "itemTag": "@ITEMS_T5_HEAD_LEATHER_SET3",
    "selectedMarket": "Martlock",
    "otherMarket": "Black Market",
    "Buying_Price": 2105000,
    "Selling_Price": 23360,
    "silver_profit": -2081640,
    "Ratio": -89.11130136986301
  }
]